Workbook

Sheet LIQ
A1: MIS EXPENSAS- Liquidación de | G1: MES: | H1: 46143
A2: ADMINISTRACION: | G2: CONSORCIO DE PROPIETARIOS:
A3: MARIANO CAUVIN | G3: LIMA 461/67/73 C.A.B.A.
A4: AV.BELGRANO 1270 5°A C.A.B.A. | G4: CUIT: 30-53267348-4
A5: masoca_administraciones@hotmail.com | F5: 4381-0014 | G5: CLAVE SUTERH: 5073
A6: 20-16975070-0 | F6: Responsable Monotributo
A7: R.P.A. N° 470 | F7: URGENCIAS 155248-3729
B9: PAGOS DEL PERIODO | G9: GASTOS "A" y "B" | H9: TOTAL | I9: %
B10: REMUNERACIONES AL PERSONAL Y CARGAS SOCIALES | K10: EFECTIVO | L10: BANCO | M10: A DEBITAR | N10: TOTAL
B11: Conf. Art. 10 inc.d Ley N°941
A12: 1 | B12: DETALLE DE SUELDOS Y CARGAS SOCIALES: | H12: =SUM(G13:G29) -> 1444814.7 | I12: =+H12/H72 -> 0.46836554 | K12: 0 | L12: =+G24+G25+G26+G27+G28+G29 -> 656057.69 | M12: =+G14 -> 788757 | N12: =SUM(K12:M12) -> 1444814.7
B13: Encargado no permanente sin vivienda 3°categoría:
B14: Giacomo Sebastian (20-36064777-4): sueldo neto 05/26 | G14: 788757
B15: Sueldo básico | E15: 598586
B16: Plus por Antigüedad- 12 años | E16: 252139.2
B17: Retiro de residuos | E17: 15527.2
B18: Clasif.de residuos Res 243/13 SSRT CABA | E18: 33429.7
B19: Adicional viáticos | E19: 73765.1
B20: Adicional remuneratorio | E20: 40000
B21: Total bruto | E21: =SUM(E15:E20) -> 1013447.2
B22: Dtos legales | E22: -224690.52
B23: Sueldo neto | E23: =SUM(E21:E22) -> 788756.68
B24: ARCA AFIP F 931: Cargas sociales: SIJP y Obra social 04/26 | G24: 410153.67
B25: ARCA AFIP 931 : ART 04/26 | G25: 111523.28
B26: ARCA AFIP 931: Seguro colectivo de vida obligatorio SCVO 04/26 | G26: 424.62
B27: SUTERH 04/26 | G27: 43958.79
B28: FATERYH 04/26 | G28: 85113.02
B29: FATERYH-SERACARH 04/26 | G29: 4884.31
B31: PAGOS POR SUMINISTROS, SERVICIOS, ABONOS Y SEGUROS
B32: Conf. Art. 10 inc. e y f Ley N°941
A33: 2 | B33: SERVICIOS PUBLICOS Y TASAS | H33: =SUM(G34:G36) -> 103423.53 | I33: =+H33/H72 -> 0.033526803 | K33: 0 | L33: =+G34+G36 -> 103423.53 | M33: 0 | N33: =SUM(K33:M33) -> 103423.53
B34: Edesur Edificio cliente 324471. Periodo 5. Débito 21/05 | G34: 98497.83
B35: Edesur Portería cliente 324475. Periodo 5. Vto. 29/05 | G35: 0
B36: Metrogas Medidor 16219365 28/02 al 31/03 liq. 1/2 | G36: 4925.7
A38: 3 | B38: ABONOS DE SERVICIOS | H38: =SUM(G39:G44) -> 446280 | I38: =+H38/H72 -> 0.14467058 | K38: 0 | L38: =+G39+G40+G43+G44 -> 366280 | M38: 0 | N38: =SUM(K38:M38) -> 366280
B39: EMEGA SRL (30-71582332-9): abono mantenimiento ascensor 04/26 FC 49247 | G39: 125000 | M39: ,
B40: MAFRAP (30-64714402-7): serv. de desinsectación 04/26 FC 180556 | G40: 81490
B41: MAFRAP (30-64714402-7): desratización, colocación de cebos, monitoreo y control 2 semanas
B42: FC 181104 | G42: 80000
B43: Machinandiarena (20-06144196-5): limpieza tanques de agua potable. Cuota 1/6 FC 1505 | G43: 70000
B44: Telecom Arg. S.A. (30-63945373-8): servicio de internet p/cámaras. Débito 5/05 | G44: 89790
A46: 4 | B46: MANTENIMIENTO DE PARTES COMUNES | H46: =SUM(G47:G50) -> 256967.09 | I46: =+H46/H72 -> 0.083301015 | K46: 0 | L46: =+G49+G50 -> 256967.09 | M46: 0 | N46: =SUM(K46:M46) -> 256967.09
B47: Tesla (20-38668041-9): instalación de contactor y llave de 3 posiciones en tablero de bomba de agua,
B48: calibrado con rele térmico y puesta en funcionamiento. Reconexión de contactores para ambas bombas
B49: FC 2344 | G49: 150000
B50: Materiales para trabajo en tablero de bomba FCs 116531/3685/3285 | G50: 106967.09
A52: 5 | B52: TRABAJOS DE REPARACIONES EN UNIDADES | H52: 0 | I52: =+H52/H72 -> 0 | K52: 0 | L52: 0 | M52: 0 | N52: =SUM(K52:M52) -> 0
A54: 6 | B54: GASTOS BANCARIOS | H54: =SUM(G55:G55) -> 112844.53 | I54: =+H54/H72 -> 0.036580809 | K54: 0 | L54: =+H54 -> 112844.53 | M54: 0 | N54: =SUM(K54:M54) -> 112844.53
B55: Banco Santander, Cta. Cte. N° 210-001950/3: gastos bancarios e imptos. 05/26 | G55: 112844.53
A57: 7 | B57: GASTOS DE LIMPIEZA | H57: =+G58 -> 42860 | I57: =+H57/H72 -> 0.013893925 | K57: =+H57 -> 42860 | L57: 0 | M57: 0 | N57: =SUM(K57:M57) -> 42860
B58: Susana y Tonino (27-10984965-6): arts de limpieza FC 7713 compensa UF 8 | G58: 42860
A60: 8 | B60: GASTOS DE ADMINISTRACIÓN Y LEGALES | H60: =SUM(G61:G61) -> 500000 | I60: =+H60/H72 -> 0.16208499 | J60: CAMB 10/26 | K60: 0 | L60: 0 | M60: =+G61 -> 500000 | N60: =SUM(K60:M60) -> 500000 | Q60: ASAMBLEA ORDINARIA 07/04/21
B61: Honorarios Administración 05/26 | G61: 500000 | Q61: 2 LIMP TANQUE Y FUMIG MENSUAL
A63: 9 | B63: SEGUROS | H63: =SUM(G65:G69) -> 177611.57 | I63: =+H63/H72 -> 0.057576338 | L63: =+H63 -> 177611.57 | M63: 0 | N63: =SUM(K63:M63) -> 177611.57
B64: Allianz (30-50003721-7): seguro integral de consorcio. Póliza N° 250230768175
B65: vigencia 31/08/2025 al 31/08/2026. Cuota 9/10 | G65: 166096.67
B66: Allianz (30-50003721-7): seguro integral de consorcio. Póliza N° 250230768175
B67: vigencia 03/03/2026 al 31/08/2026. Endoso Cuota 2/3 | G67: 8299
B68: Berkley: seguro de vida colectivo. Póliza 37526 vigencia 01/10/25 al 01/10/26.
B69: Cuota 8/10 | G69: 3215.9
A71: 10 | B71: OTROS | H71: 0 | I71: =+H71/H72 -> 0 | K71: 0 | L71: 0 | M71: 0 | N71: =SUM(K71:M71) -> 0
B72: Total de pagos | G72: =SUM(G12:G71) -> 3084801.4 | H72: =SUM(H12:H71) -> 3084801.4 | I72: =+H72/H72 -> 1 | K72: =SUM(K12:K71) -> 42860 | L72: =SUM(L12:L71) -> 1673184.4 | M72: =SUM(M12:M71) -> 1288757 | N72: =SUM(N12:N71) -> 3004801.4 | O72: =+H72 -> 3084801.4 | P72: =+N72-O72 -> -80000
B73: PREVISIONES/PROVISIONES | H73: =SUM(G74:G76) -> 7900000
B74: ARCA AFIP, FATERYH, SUTERH 04/26 | G74: -800000
B75: ARCA AFIP, FATERYH, SUTERH 05/26 | G75: 800000
B76: S/lo resuelto en Asamblea 20/04/26 | G76: =15800000/2 -> 7900000 | K76: recaudar en mayo s/Asmblea 20/04/26 $ 15,800,000
B77: Total de previsiones | G77: =SUM(G74:G76) -> 7900000 | H77: =SUM(H73:H73) -> 7900000
B78: Total prorrateo | G78: =+G72+G77 -> 10984801 | H78: =+H72+H77 -> 10984801
B80: ESTADO FINANCIERO | G80: CAJA | L80: BANCO
B81: Conf. Art. 10 inc. c Ley N°941
B82: Saldo anterior | G82: =+[1]LIQ!$G$86 -> 7515886.1 | K82: Saldo inicial | L82: 8694516.9 | M82: 81900 | N82: -1260371 | O82: =SUM(L82:N82) -> 7516045.9 | P82: =+G82 -> 7515886.1 | Q82: =+O82-P82 -> 159.82761
B83: Cobranzas por expensas del período | G83: =+'RES CUENTA'!Z25+'RES CUENTA'!AA25 -> 3355141 | K83: Cobranzas del mes | L83: =+'RES CUENTA'!Z25 -> 3312281 | M83: =+'RES CUENTA'!AA25 -> 42860 | N83: 0 | O83: =SUM(L83:N83) -> 3355141 | P83: =+G83 -> 3355141 | Q83: =+O83-P83 -> 0
B84: Cobranzas bancarias del período sin identificar | G84: =+L84 -> 0 | K84: Cobranzas sin ID | M84: 0 | N84: 0 | O84: =SUM(L84:N84) -> 0 | P84: =+G84 -> 0 | Q84: =+O84-P84 -> 0
B85: Cobranzas bancarias de meses anteriores aplicadas este período | G85: =+L85 -> 0 | K85: Cob identif este mes | L85: =+'RES CUENTA'!Z26 -> 0 | O85: =SUM(L85:N85) -> 0 | P85: =+G85 -> 0 | Q85: =+O85-P85 -> 0
B86: Pagos del período Gastos A y B | G86: =-G72 -> -3084801.4 | K86: Gastos del mes | L86: =-G55-G24-G25-G26-G27-G28-G29-G67-G36-G44-G39-G40-G42-G43-G65-G69-G34 -> -1496217.3 | M86: =-K72 -> -42860 | N86: =-M72 -> -1288757 | O86: =SUM(L86:N86) -> -2827834.3 | P86: =+G86 -> -3084801.4 | Q86: =+O86-P86 -> 256967.09
B87: Saldo al cierre | G87: =SUM(G82:G86) -> 7786225.7 | K87: Gastos del mes anterior | L87: =-500000-760371 -> -1260371 | M87: 0 | N87: =-L87-M87 -> 1260371 | O87: =SUM(L87:N87) -> 0 | P87: 0 | Q87: =+O87-P87 -> 0
K88: Retiro/deposito | L88: =-106967.09-150000 -> -256967.09 | M88: =-N88 -> 0 | N88: 0 | O88: =SUM(L88:N88) -> -256967.09 | P88: 0 | Q88: =+O88-P88 -> -256967.09
K89: SALDO | L89: =SUM(L82:L88) -> 8993242.5 | M89: =SUM(M82:M88) -> 81900 | N89: =SUM(N82:N88) -> -1288757 | O89: =SUM(L89:N89) -> 7786385.5 | P89: =SUM(P82:P88) -> 7786225.7 | Q89: =+O89-P89 -> 159.82761
K90: SALDO S/EXTRACT | L90: 8993242.5 | M90: =+L95+L98+L99 -> 81900 | N90: =+L92 -> -1288757 | Q90: =+O90-P90 -> 0
J91: =+L92-L87-M87 -> -28386 | L91: =+L89-L90 -> 0 | M91: =+M89-M90 -> 0 | N91: =+N89-N90 -> 0 | Q91: =+O91-P91 -> 0
B92: Aporte comprometido en Asamblea Extraordinaria 12/04/21 por UF1 Anticipo y saldo de obra | J92: 0 | K92: a debitar | L92: =-500000-788757 -> -1288757 | M92: ch 863 $ 6200 esde 05/2023 v destap presentado al bco en 07/2023 y rechazado por vencido plazo legal, se retira efectivo en 11/2025
B93: UF 2 | D93: =22909+22909 -> 45818 | F93: 0
B94: UF 3 | D94: =10985*2 -> 21970 | J94: =+J91-J92 -> -28386 | K94: SALDO EN BANCO | L94: =+L90+L92 -> 7704485.5
B95: UF 4 | D95: =10985*2 -> 21970 | J95: =10937.96+31549.62 -> 42487.58 | K95: EFECTIVO | L95: 81900
B96: UF 5 | D96: =11092+1092 -> 12184 | F96: 10000 | K96: EFECTIVO ANTICIPO | L96: 0
B97: UF 6 | D97: =11092*2 -> 22184 | K97: EFECTIVO ANT UF 1 | L97: 0
B98: UF 7 | D98: =11200+11200 -> 22400 | J98: 27406.11 | K98: YA PAGADO | L98: 0
B99: UF 8 | D99: =11200*2 -> 22400 | J99: =-1425.2-720-4300-4300 -> -10745.2 | K99: LE DEBEN | L99: 0
B100: UF 9 | D100: =10878*2 -> 21756 | J100: =+J98+J99 -> 16660.91 | K100: TOTAL ARQUEO | L100: =SUM(L94:L99) -> 7786385.5
B101: UF 10 | D101: =10878*2 -> 21756 | K101: TOTAL LIQUIDACION | L101: =+G87 -> 7786225.7
D102: =SUM(D93:D101) -> 212438 | F102: =SUM(F93:F101) -> 10000 | G102: =+F102+D102 -> 222438 | K102: SOBRANTE | L102: =+L100-L101 -> 159.82761 | M102: se genera saldo a favor por ch de seguro era por $ 3616 y se debito $ 3238
B104: AFIP F 931: Cargas sociales: SIJP y Obra social 05/26 | G104: =147082.99+190390.92+29468.79+58937.59 -> 425880.29
B105: AFIP 931 : ART 05/26 | G105: 115676.47
B106: AFIP 931: Seguro colectivo de vida obligatorio SCVO 05/26 | G106: 424.62
B107: SUTERH 05/26 | G107: =+SUELDO!I61-0.01 -> 45605.124
B108: FATERYH 05/26 | G108: =+SUELDO!M61+44962/2-0.01 -> 88355.058
B109: SERACARH 05/26 | G109: =+SUELDO!O61 -> 5067.236
B110: SERACARH- Capacitación
B111: 2° aguinaldo y bonificación anual
G112: =SUM(G104:G111) -> 681008.8
...

Sheet RES CUENTA
A3: =+LIQ!A2 -> ADMINISTRACION: | P3: =+LIQ!G2 -> CONSORCIO DE PROPIETARIOS: | X3: Gastos comunes f
A4: =+LIQ!A3 -> MARIANO CAUVIN | P4: =+LIQ!G3 -> LIMA 461/67/73 C.A.B.A. | X4: Cuidado reparación y gastos por ascensores quedando excluido por esta contribucion los locales de PB
A5: =+LIQ!A4 -> AV.BELGRANO 1270 5°A C.A.B.A. | P5: =+LIQ!G4 -> CUIT: 30-53267348-4
A6: =+LIQ!A5 -> masoca_administraciones@hotmail.com | G6: =+LIQ!F5 -> 4381-0014 | P6: =+LIQ!G5 -> CLAVE SUTERH: 5073
A7: =+LIQ!A6 -> 20-16975070-0 | G7: =+LIQ!F6 -> Responsable Monotributo
A8: =+LIQ!A7 -> R.P.A. N° 470 | G8: =+LIQ!F7 -> URGENCIAS 155248-3729
A10: ESTADO DE CUENTAS Y PRORRATEO DE GASTOS AL 31/05/2026 | Z10: compensa
A11: AVISO DE PAGO : FECHA DE VENCIMIENTO 15/06/2026
Z13: Cobranza | AB13: Saldo Obra | AD13: UF1 Saldo
A14: DTO | B14: U.F. | C14: DTO | D14: NOMBRE | E14: SALDO ANTERIOR | F14: SU PAGO | G14: % A | H14: %B | L14: EXP. A | M14: EXP. B | N14: CABLE | O14: OTROS | P14: TOTALES DEL MES | Q14: DEUDA | R14: INTERE-SES | S14: TOTAL | T14: FONDO | U14: OBSERVACIONES | V14: OBSERVACIONES | W14: U.F. | X14: Dif | Y14: S/ liquid | Z14: BANCO | AA14: EFVO | AB14: BANCO | AC14: EFVO | AD14: BANCO | AE14: EFVO
A15: Local | B15: 1 | C15: 1-A | D15: Casa Lopez | E15: =+Y15 -> 25146047 | F15: =-Z15-AA15 -> 0 | G15: 17.08 | H15: 0 | I15: =+(G15+H15)/2 -> 8.54 | J15: =+(0.0631221170186939)*100 -> 6.3122117 | K15: =+I15-J15 -> 2.2277883 | L15: =+$L$25*G15/100 -> 1854854.1 | M15: =+$L$25*H15/100 -> 0 | N15: 0 | O15: 0 | P15: =SUM(L15:N15) -> 1854854.1 | Q15: =+INTERESES!D9+INTERESES!E10+INTERESES!F11+INTERESES!G12+INTERESES!H13+INTERESES!I14+INTERESES!J15+INTERESES!K16+INTERESES!L17+INTERESES!M18+INTERESES!N19+INTERESES!O20+INTERESES!P21+INTERESES!Q22+INTERESES!R23+INTERESES!S24+INTERESES!T25+INTERESES!U26+INTERESES!V27+INTERESES!W28+INTERESES!X29+INTERESES!Y30+INTERESES!Z31+INTERESES!AA32+INTERESES!AB33+INTERESES!AC34+INTERESES!AD35+INTERESES!AE36+INTERESES!AF37+INTERESES!AG38+INTERESES!AH39+INTERESES!AI40+INTERESES!AJ41+INTERESES!AK42+INTERESES!AL43+INTERESES!AM44+INTERESES!AN45+INTERESES!AO46+INTERESES!AP47+INTERESES!AQ48+INTERESES!AR49+INTERESES!AS50+INTERESES!AT51+INTERESES!AU52+INTERESES!AV53+INTERESES!AW54+INTERESES!AX55+INTERESES!AY56+INTERESES!AZ57+INTERESES!BA58+INTERESES!BB59+INTERESES!BC60+INTERESES!BD61+INTERESES!BE62+INTERESES!BF63+INTERESES!BG64+INTERESES!BH65+INTERESES!BI66+INTERESES!BJ67+INTERESES!BK68+INTERESES!BL69+INTERESES!BM70+INTERESES!BN71+INTERESES!BO72+INTERESES!BP73+INTERESES!BQ74+INTERESES!BR75+INTERESES!BS76+INTERESES!BT77+INTERESES!BU78+INTERESES!BV79+INTERESES!BW80+INTERESES!BX81+INTERESES!BY82+INTERESES!BZ83+INTERESES!CA84+INTERESES!CB85+INTERESES!CC86+INTERESES!CD87+INTERESES!CE88+INTERESES!CF89+INTERESES!CG90+INTERESES!CH91+INTERESES!CI92+INTERESES!CJ93+INTERESES!CK94+INTERESES!CL95+INTERESES!CM96+INTERESES!CN97+INTERESES!CO98+INTERESES!CP99+INTERESES!CQ100+INTERESES!CR101+INTERESES!CS102+INTERESES!CT103+INTERESES!CU104+INTERESES!CV105+INTERESES!CW106+INTERESES!CX107+INTERESES!CY108 -> 16679327 | R15: =+INTERESES!DB109 -> 8967099.7 | S15: =+P15+Q15+R15 -> 27501281 | T15: 0 | W15: 1 | X15: =+Y15-Z15-AA15-AB15-AC15-AD15-AE15 -> 25146047 | Y15: 25146047 | AF15: =+R15 -> 8967099.7 | AG15: 0 | AH15: =+AF15-AG15 -> 8967099.7 | AJ15: =+S15-Z15 -> 27501281 | AK15: =+AJ15/Z15 -> #DIV/0!
A16: Local | B16: =+B15+1 -> 2 | C16: 1-B | D16: Eduardo Sanchez | E16: =+Y16 -> 736215.86 | F16: =-Z16-AA16 -> -736216 | G16: 17.08 | H16: 0 | I16: =+(G16+H16)/2 -> 8.54 | J16: =+(0.0407865986890022)*100 -> 4.0786599 | K16: =+I16-J16 -> 4.4613401 | L16: =+$L$25*G16/100 -> 1854854.1 | M16: =+$L$25*H16/100 -> 0 | N16: 0 | O16: 0 | P16: =SUM(L16:N16) -> 1854854.1 | Q16: 0 | R16: 0 | S16: =SUM(P16:R16) -> 1854854.1 | T16: 0 | W16: =+W15+1 -> 2 | X16: =+Y16-Z16-AA16-AB16-AC16-AD16-AE16 -> -0.14116 | Y16: 736215.86 | Z16: 736216 | AF16: =+R16 -> 0 | AG16: 0 | AH16: =+AF16-AG16 -> 0 | AJ16: =+S16-Z16 -> 1118638.1 | AK16: =+AJ16/Z16 -> 1.5194428 | AN16: soporte@casasanchez.com.ar
A17: 1A | B17: =+B16+1 -> 3 | C17: 2-A | D17: Benjamin Fernandez | E17: =+Y17 -> 367327.54 | F17: =-Z17-AA17 -> -397028 | G17: 8.19 | H17: 12.44 | I17: =+(G17+H17)/2 -> 10.315 | J17: =+(0.0485554746297645)*100 -> 4.8555475 | K17: =+I17-J17 -> 5.4594525 | L17: =+$L$25*G17/100 -> 889417.74 | M17: =+$M$25*H17/100 -> 15550 | N17: 0 | O17: 0 | P17: =SUM(L17:N17) -> 904967.74 | Q17: -29700 | R17: 0 | S17: =SUM(P17:R17) -> 875267.74 | T17: 0 | W17: =+W16+1 -> 3 | X17: =+Y17-Z17-AA17-AB17-AC17-AD17-AE17 -> -29700.461 | Y17: 367327.54 | Z17: =764356-367328 -> 397028 | AF17: =+R17 -> 0 | AG17: 0 | AH17: =+AF17-AG17 -> 0 | AJ17: =+S17-Z17 -> 478239.74 | AK17: =+AJ17/Z17 -> 1.2045491 | AN17: lippifranco0@gmail.com
A18: 1B | B18: =+B17+1 -> 4 | C18: 2-B | D18: Franco Lippi | E18: =+Y18 -> 367327.54 | F18: =-Z18-AA18 -> -367328 | G18: 8.19 | H18: 12.44 | I18: =+(G18+H18)/2 -> 10.315 | J18: =+(0.0405438213158534)*100 -> 4.0543821 | K18: =+I18-J18 -> 6.2606179 | L18: =+$L$25*G18/100 -> 889417.74 | M18: =+$M$25*H18/100 -> 15550 | N18: 0 | O18: 0 | P18: =SUM(L18:N18) -> 904967.74 | Q18: 0 | R18: 0 | S18: =SUM(P18:R18) -> 904967.74 | T18: 0 | W18: =+W17+1 -> 4 | X18: =+Y18-Z18-AA18-AB18-AC18-AD18-AE18 -> -0.46113 | Y18: 367327.54 | Z18: 367328 | AF18: =+R18 -> 0 | AG18: 0 | AH18: =+AF18-AG18 -> 0 | AJ18: =+S18-Z18 -> 537639.74 | AK18: =+AJ18/Z18 -> 1.4636503 | AN18: lippifranco0@gmail.com
A19: 2C | B19: =+B18+1 -> 5 | C19: 3-A | D19: Antonella Denegri | E19: =+Y19 -> 370913.86 | F19: =-Z19-AA19 -> -370914 | G19: 8.27 | H19: 12.56 | I19: =+(G19+H19)/2 -> 10.415 | J19: =+(0.0490410293760622)*100 -> 4.9041029 | K19: =+I19-J19 -> 5.5108971 | L19: =+$L$25*G19/100 -> 898105.58 | M19: =+$M$25*H19/100 -> 15700 | N19: 0 | O19: 0 | P19: =SUM(L19:N19)+O19 -> 913805.58 | Q19: 0 | R19: 0 | S19: =SUM(P19:R19) -> 913805.58 | T19: 0 | W19: =+W18+1 -> 5 | X19: =+Y19-Z19-AA19-AB19-AC19-AD19-AE19 -> -0.14329 | Y19: 370913.86 | Z19: 370914 | AF19: =+R19 -> 0 | AG19: 0 | AH19: =+AF19-AG19 -> 0 | AJ19: =+S19-Z19 -> 542891.58 | AK19: =+AJ19/Z19 -> 1.4636589 | AN19: audinomarta@yahoo.com.ar
A20: 2D | B20: =+B19+1 -> 6 | C20: 3-B | D20: Ana Isabel Pirro | E20: =+Y20 -> 370913.86 | F20: =-Z20-AA20 -> -370914 | G20: 8.27 | H20: 12.56 | I20: =+(G20+H20)/2 -> 10.415 | J20: =+(0.0407865986890022)*100 -> 4.0786599 | K20: =+I20-J20 -> 6.3363401 | L20: =+$L$25*G20/100 -> 898105.58 | M20: =+$M$25*H20/100 -> 15700 | N20: 0 | O20: 0 | P20: =SUM(L20:N20) -> 913805.58 | Q20: 0 | R20: 0 | S20: =SUM(P20:R20) -> 913805.58 | T20: 0 | W20: =+W19+1 -> 6 | X20: =+Y20-Z20-AA20-AB20-AC20-AD20-AE20 -> -0.14329 | Y20: 370913.86 | Z20: 370914 | AF20: =+R20 -> 0 | AG20: 0 | AH20: =+AF20-AG20 -> 0 | AJ20: =+S20-Z20 -> 542891.58 | AK20: =+AJ20/Z20 -> 1.4636589 | AM20: Transferencia Recibida - De Renki/ Marcia Aleja / Enero 2021 - Exp / 27242954128 | AN20: anabel.pirro@gmail.com | AO20: Transferencia Recibida - De Martin/morales Manuel / 2 D - Exp / 23252272879
A21: 3E | B21: =+B20+1 -> 7 | C21: 4-A | D21: Leandro Acero | E21: =+Y21 -> 374500.17 | F21: =-Z21-AA21 -> -374500 | G21: 8.35 | H21: 12.68 | I21: =+(G21+H21)/2 -> 10.515 | J21: =+(0.0490410293760622)*100 -> 4.9041029 | K21: =+I21-J21 -> 5.6108971 | L21: =+$L$25*G21/100 -> 906793.42 | M21: =+$M$25*H21/100 -> 15850 | N21: 0 | O21: 0 | P21: =SUM(L21:N21) -> 922643.42 | Q21: 0 | R21: 0 | S21: =SUM(P21:R21) -> 922643.42 | T21: 0 | W21: =+W20+1 -> 7 | X21: =+Y21-Z21-AA21-AB21-AC21-AD21-AE21 -> 0.17455 | Y21: 374500.17 | Z21: 374500 | AF21: =+R21 -> 0 | AG21: 0 | AH21: =+AF21-AG21 -> 0 | AJ21: =+S21-Z21 -> 548143.42 | AK21: =+AJ21/Z21 -> 1.4636673 | AM21: lomas/acero | AN21: escribaniaacero@hotmail.com.ar
A22: 3F | B22: =+B21+1 -> 8 | C22: 4-B | D22: Jose A. Montans | E22: =+Y22 -> 374500.17 | F22: =-Z22-AA22 -> -374500 | G22: 8.35 | H22: 12.68 | I22: =+(G22+H22)/2 -> 10.515 | J22: =+(0.041029376062151)*100 -> 4.1029376 | K22: =+I22-J22 -> 6.4120624 | L22: =+$L$25*G22/100 -> 906793.42 | M22: =+$M$25*H22/100 -> 15850 | N22: 0 | O22: 0 | P22: =SUM(L22:N22) -> 922643.42 | Q22: 0 | R22: 0 | S22: =SUM(P22:R22) -> 922643.42 | T22: 0 | W22: =+W21+1 -> 8 | X22: =+Y22-Z22-AA22-AB22-AC22-AD22-AE22 -> 0.17455 | Y22: 374500.17 | Z22: 331640 | AA22: =+LIQ!G58 -> 42860 | AF22: =+R22 -> 0 | AG22: 0 | AH22: =+AF22-AG22 -> 0 | AJ22: =+S22-738 -> 921905.42 | AK22: =+AJ22/738 -> 1249.1943 | AN22: susanabveiga@hotmail.com
A23: 4G | B23: =+B22+1 -> 9 | C23: 5-A | D23: Miguel A. Machinandiarena | E23: =+Y23 -> 363741.22 | F23: =-Z23-AA23 -> -363741 | G23: 8.11 | H23: 12.32 | I23: =+(G23+H23)/2 -> 10.215 | J23: =+(205/4119)*100 -> 4.9769361 | K23: =+I23-J23 -> 5.2380639 | L23: =+$L$25*G23/100 -> 880729.89 | M23: =+$M$25*H23/100 -> 15400 | N23: 0 | O23: 0 | P23: =SUM(L23:N23) -> 896129.89 | Q23: 0 | R23: 0 | S23: =SUM(P23:R23) -> 896129.89 | T23: 0 | W23: =+W22+1 -> 9 | X23: =+Y23-Z23-AA23-AB23-AC23-AD23-AE23 -> 0.22103 | Y23: 363741.22 | Z23: 363741 | AF23: =+R23 -> 0 | AG23: 0 | AH23: =+AF23-AG23 -> 0 | AJ23: =+S23-717 -> 895412.89 | AK23: =+AJ23/717 -> 1248.8325 | AN23: machifumigaciones@hotmail.com
A24: 4H | B24: =+B23+1 -> 10 | C24: 5-B | D24: Olivier Liem | E24: =+Y24 -> 1066890.5 | F24: =-Z24-AA24 -> 0 | G24: 8.11 | H24: 12.32 | I24: =+(G24+H24)/2 -> 10.215 | J24: =+(0.0422432629278951)*100 -> 4.2243263 | K24: =+I24-J24 -> 5.9906737 | L24: =+$L$25*G24/100 -> 880729.89 | M24: =+$M$25*H24/100 -> 15400 | N24: 0 | O24: 0 | P24: =SUM(L24:N24) -> 896129.89 | Q24: =+INTERESES!CV141+INTERESES!CW142+INTERESES!CX143+INTERESES!CY144 -> 1046410.5 | R24: =+INTERESES!DB145 -> 51872.391 | S24: =SUM(P24:R24) -> 1994412.7 | T24: 0 | W24: =+W23+1 -> 10 | X24: =+Y24-Z24-AA24-AB24-AC24-AD24-AE24 -> 1066890.5 | Y24: 1066890.5 | AF24: =+R24 -> 51872.391 | AG24: 43.012634 | AH24: =+AF24-AG24 -> 51829.378 | AI24: cob y genrera | AJ24: =+S24-590 -> 1993822.7 | AK24: =+AJ24/590 -> 3379.3606 | AN24: olivier.liem@yahoo.fr
D25: TOTALES | E25: =SUM(E15:E24) -> 29538378 | F25: =SUM(F15:F24) -> -3355141 | G25: =SUM(G15:G24) -> 100 | H25: =SUM(H15:H24) -> 100 | I25: =SUM(I15:I24) -> 100 | J25: =SUM(J15:J24) -> 46.491867 | K25: =SUM(K15:K24) -> 53.508133 | L25: =+LIQ!G78-LIQ!G39 -> 10859801 | M25: =+LIQ!G39 -> 125000 | N25: =SUM(N15:N24) -> 0 | O25: =SUM(O15:O24) -> 0 | P25: =SUM(P15:P24) -> 10984801 | Q25: =SUM(Q15:Q24) -> 17696038 | R25: =SUM(R15:R24) -> 9018972.1 | S25: =SUM(S15:S24) -> 37699811 | X25: =+Y25-Z25-AA25 -> 26183237 | Y25: 29538378 | Z25: =SUM(Z15:Z24) -> 3312281 | AA25: =SUM(AA15:AA24) -> 42860 | AB25: =SUM(AB15:AB24) -> 0 | AC25: =SUM(AC15:AC24) -> 0 | AD25: =SUM(AD15:AD24) -> 0 | AE25: =SUM(AE15:AE24) -> 0 | AF25: =+R25 -> 9018972.1 | AG25: 43.012634 | AH25: =+AF25-AG25 -> 9018929.1
Z26: 0
A27: LAS EXPENSAS VENCEN EL DIA 15. PAGO FUERA DE TERMINO 3% DE INTERÉS MENSUAL | U27: =60393.6-50960.07-1482.12+84 -> 8035.41 | Z27: =+Z25+AA25 -> 3355141 | AF27: 7942
Z29: 2116582
A30: FORMAS DE PAGO: | Z30: =+Z27-Z29 -> 1238559
A31: Depósito o transferencia:
A32: Titular: | D32: CONSORCIO DE PROP. LIMA 461
A33: Banco: | D33: SANTANDER
A34: N°Cuenta: | D34: Cta. Cte. $ N°210-001950/3 | U34: =+LIQ!G83 -> 3355141 | Z34: =+Z25+AA25 -> 3355141 | AB34: =+AB25+AC25 -> 0
A35: CBU: | D35: 0720210220000000195036 | U35: =+U27-U34 -> -3347105.6 | Z35: 444270
A36: Alias: | D36: BOCHA.CARDO.COPA
A39: DATOS DE JUICIOS
A40: Conf. Art. 10 inc. h Ley N°941
A42: CARATULA: Cons. de Prop. Lima 461/67/73 c/Lopez Jose y otro s /Ejecución de Expensas
A43: N° EXPEDIENTE: 68063/2018
A44: JUZGADO/SECRETARÍA: Juzgado Civil N° 75
A45: ESTADO: embargo trabado
A46: MONTO RECLAMADO:
A49: MANUAL DE BUENAS PRÁCTICAS CONSORCIALES
A50: https://buenosaires.gob.ar/sites/default/files/2025-02/Manual%20buenas%20pr%C3%A1cticas%20consorciales_0.pdf
A52: REGLAMENTO DE COPROPIEDAD
A53: https://drive.google.com/file/d/1eKPMIGdXOZSUk3VRB9ujPuaYYa1R6ep-/view?usp=drive_link
A55: APORTES Y CONTRIBUCIONES
... A64: APORTE COMPROMETIDO EN ASAMBLEA EXTRAORDINARIA DEL 12/04/21 PARA LA OBRA POR UF. 1
A67: DTO | B67: U.F. | C67: DTO | D67: NOMBRE | E67: APORTE
A68: Local | B68: 2 | C68: 1-B | D68: Eduardo Sanchez | E68: =22909+22909 -> 45818
A69: 1A | B69: 3 | C69: 2-A | D69: Benjamin Fernandez | E69: =10985*2 -> 21970
A70: 1B | B70: 4 | C70: 2-B | D70: Franco Lippi | E70: =10985*2 -> 21970
A71: 2C | B71: 5 | C71: 3-A | D71: Marta Audino | E71: =11092+1092+10000 -> 22184
A72: 2D | B72: 6 | C72: 3-B | D72: Ana Isabel Pirro | E72: =11092*2 -> 22184
A73: 3E | B73: 7 | C73: 4-A | D73: D.J. Wainer | E73: =11200+11200 -> 22400
A74: 3F | B74: 8 | C74: 4-B | D74: Jose A. Montans | E74: =11200*2 -> 22400
A75: 4G | B75: 9 | C75: 5-A | D75: Miguel A. Machinandiarena | E75: =10878*2 -> 21756
A76: 4H | B76: 10 | C76: 5-B | D76: Olivier Liem | E76: =10878*2 -> 21756
E77: =SUM(E68:E76) -> 222438
G106: =690552.16-150241.66-334.68 -> 539975.82
G107: 150241.66
G109: =+SUELDO!I61 -> 45605.134
G110: =+SUELDO!M61+26264/2-0.01 -> 79006.058

Sheet INTERESES
A2: =+'RES CUENTA'!#REF! -> #REF!
A7: U.F. | B7: DTO | C7: NOMBRE | D7: 43101 | E7: 43132 | F7: 43160 | G7: 43191 | H7: 43221 | I7: 43252 | J7: 43282 | K7: 43313 | L7: 43344 | M7: 43374 | N7: 43405 | O7: 43435 | P7: 43466 | Q7: 43497 | R7: 43525 | S7: 43556 | T7: 43586 | U7: 43617 | V7: 43647 | W7: 43678 | X7: 43709 | Y7: 43739 | Z7: 43770 | AA7: 43800 | AB7: 43831 | AC7: 43862 | AD7: 43891 | AE7: 43922 | AF7: 43952 | AG7: 43983 | AH7: 44013 | AI7: 44044 | AJ7: 44075 | AK7: 44105 | AL7: 44136 | AM7: 44166 | AN7: 44197 | AO7: 44228 | AP7: 44256 | AQ7: 44287 | AR7: 44317 | AS7: 44348 | AT7: 44378 | AU7: 44409 | AV7: 44440 | AW7: 44470 | AX7: 44501 | AY7: 44531 | AZ7: 44562 | BA7: 44593 | BB7: 44621 | BC7: 44652 | BD7: 44682 | BE7: 44713 | BF7: 44743 | BG7: 44774 | BH7: 44805 | BI7: 44835 | BJ7: 44866 | BK7: 44896 | BL7: 44927 | BM7: 44958 | BN7: 44986 | BO7: 45017 | BP7: 45047 | BQ7: 45078 | BR7: 45108 | BS7: 45139 | BT7: 45170 | BU7: 45200 | BV7: 45231 | BW7: 45261 | BX7: 45292 | BY7: 45323 | BZ7: 45352 | CA7: 45383 | CB7: 45413 | CC7: 45444 | CD7: 45474 | CE7: 45505 | CF7: 45536 | CG7: 45566 | CH7: 45597 | CI7: 45627 | CJ7: 45658 | CK7: 45689 | CL7: 45717 | CM7: 45748 | CN7: 45778 | CO7: 45809 | CP7: 45839 | CQ7: 45870 | CR7: 45901 | CS7: 45931 | CT7: 45962 | CU7: 45992 | CV7: 46023 | CW7: 46054 | CX7: 46082 | CY7: 46113 | CZ7: TASA | DA7: DIAS | DB7: INTERES
A9: 1 | C9: =+'RES CUENTA'!D15 -> Casa Lopez | D9: =+'[2]RES CUENTA'!$O$18 -> 6423.3473 | CZ9: 0.03 | DA9: 3000 | DB9: =+D9*CZ9/30*DA9 -> 19270.042 | DC9: =+DA9-DA10 -> 30 | DD9: =+DA9/365 -> 8.2191781
E10: =+'[3]RES CUENTA'!$O$18 -> 6906.0213 | CZ10: 0.03 | DA10: 2970 | DB10: =+E10*CZ10/30*DA10 -> 20510.883 | DC10: =+DA10-DA11 -> 30
F11: =+'[4]RES CUENTA'!$O$18 -> 9084.4506 | CZ11: 0.03 | DA11: 2940 | DB11: =+F11*CZ11/30*DA11 -> 26708.285 | DC11: =+DA11-DA12 -> 30
G12: =+'[5]RES CUENTA'!$O$18 -> 10009.988 | CZ12: 0.03 | DA12: 2910 | DB12: =+G12*CZ12/30*DA12 -> 29129.067 | DC12: =+DA12-DA13 -> 30
H13: =+'[6]RES CUENTA'!$O$18 -> 9524.0369 | CZ13: 0.03 | DA13: 2880 | DB13: =+H13*CZ13/30*DA13 -> 27429.226 | DC13: =+DA13-DA14 -> 30
I14: =+'[7]RES CUENTA'!$O$18 -> 9455.2233 | CZ14: 0.03 | DA14: 2850 | DB14: =+I14*CZ14/30*DA14 -> 26947.386 | DC14: =+DA14-DA15 -> 30
J15: =+'[8]RES CUENTA'!$O$18 -> 7258.1238 | CZ15: 0.03 | DA15: 2820 | DB15: =+J15*CZ15/30*DA15 -> 20467.909 | DC15: =+DA15-DA16 -> 30
K16: =+'[9]RES CUENTA'!$O$18 -> 10081.522 | CZ16: 0.03 | DA16: 2790 | DB16: =+K16*CZ16/30*DA16 -> 28127.447 | DC16: =+DA16-DA17 -> 30
L17: =+'[10]RES CUENTA'!$O$18 -> 9702.7529 | CZ17: 0.03 | DA17: 2760 | DB17: =+L17*CZ17/30*DA17 -> 26779.598 | DC17: =+DA17-DA18 -> 30
M18: =+'[11]RES CUENTA'!$O$18 -> 14227.098 | CZ18: 0.03 | DA18: 2730 | DB18: =+M18*CZ18/30*DA18 -> 38839.978 | DC18: =+DA18-DA19 -> 30
N19: =+'[12]RES CUENTA'!$O$18 -> 14621.914 | CZ19: 0.03 | DA19: 2700 | DB19: =+N19*CZ19/30*DA19 -> 39479.168 | DC19: =+DA19-DA20 -> 30
O20: =+'[13]RES CUENTA'!$O$18 -> 15154.505 | CZ20: 0.03 | DA20: 2670 | DB20: =+O20*CZ20/30*DA20 -> 40462.529 | DC20: =+DA20-DA21 -> 30
P21: =+'[14]RES CUENTA'!$O$18 -> 14019.754 | CZ21: 0.03 | DA21: 2640 | DB21: =+P21*CZ21/30*DA21 -> 37012.15 | DC21: =+DA21-DA22 -> 30
Q22: =+'[15]RES CUENTA'!$O$18 -> 13731.776 | CZ22: 0.03 | DA22: 2610 | DB22: =+Q22*CZ22/30*DA22 -> 35839.936 | DC22: =+DA22-DA23 -> 30
R23: =+'[16]RES CUENTA'!$O$18 -> 14197.886 | CZ23: 0.03 | DA23: 2580 | DB23: =+R23*CZ23/30*DA23 -> 36630.546 | DC23: =+DA23-DA24 -> 30
S24: =+'[17]RES CUENTA'!$O$18 -> 13290.12 | CZ24: 0.03 | DA24: 2550 | DB24: =+S24*CZ24/30*DA24 -> 33889.805 | DC24: =+DA24-DA25 -> 30
T25: =+'[18]RES CUENTA'!$O$18 -> 14125.29 | CZ25: 0.03 | DA25: 2520 | DB25: =+T25*CZ25/30*DA25 -> 35595.73 | DC25: =+DA25-DA26 -> 30
U26: =+'[19]RES CUENTA'!$O$18 -> 17870.851 | CZ26: 0.03 | DA26: 2490 | DB26: =+U26*CZ26/30*DA26 -> 44498.419 | DC26: =+DA26-DA27 -> 30
V27: =+'[20]RES CUENTA'!$O$18 -> 12458.019 | CZ27: 0.03 | DA27: 2460 | DB27: =+V27*CZ27/30*DA27 -> 30646.727 | DC27: =+DA27-DA28 -> 30
W28: =+'[21]RES CUENTA'!$O$18 -> 12797.668 | CZ28: 0.03 | DA28: 2430 | DB28: =+W28*CZ28/30*DA28 -> 31098.333 | DC28: =+DA28-DA29 -> 30
X29: =+'[22]RES CUENTA'!$O$18 -> 12868.024 | CZ29: 0.03 | DA29: 2400 | DB29: =+X29*CZ29/30*DA29 -> 30883.257 | DC29: =+DA29-DA30 -> 30
Y30: =+'[23]RES CUENTA'!$O$18 -> 15642.94 | CZ30: 0.03 | DA30: 2370 | DB30: =+Y30*CZ30/30*DA30 -> 37073.769 | DC30: =+DA30-DA31 -> 30
Z31: =+'[24]RES CUENTA'!$O$18 -> 16047.563 | CZ31: 0.03 | DA31: 2340 | DB31: =+Z31*CZ31/30*DA31 -> 37551.297 | DC31: =+DA31-DA32 -> 30
AA32: =+'[25]RES CUENTA'!$O$18 -> 16392.666 | CZ32: 0.03 | DA32: 2310 | DB32: =+AA32*CZ32/30*DA32 -> 37867.059 | DC32: =+DA32-DA33 -> 30
AB33: =+'[26]RES CUENTA'!$O$18 -> 14379.2 | CZ33: 0.03 | DA33: 2280 | DB33: =+AB33*CZ33/30*DA33 -> 32784.577 | DC33: =+DA33-DA34 -> 30
AC34: =+'[27]RES CUENTA'!$O$18 -> 14729.463 | CZ34: 0.03 | DA34: 2250 | DB34: =+AC34*CZ34/30*DA34 -> 33141.293 | DC34: =+DA34-DA35 -> 30
AD35: =+'[28]RES CUENTA'!$O$18 -> 15688.46 | CZ35: 0.03 | DA35: 2220 | DB35: =+AD35*CZ35/30*DA35 -> 34828.381 | DC35: =+DA35-DA36 -> 30
AE36: =+'[29]RES CUENTA'!$O$18 -> 15477.466 | CZ36: 0.03 | DA36: 2190 | DB36: =+AE36*CZ36/30*DA36 -> 33895.65 | DC36: =+DA36-DA37 -> 30
AF37: =+'[30]RES CUENTA'!$O$18 -> 14246.361 | CZ37: 0.03 | DA37: 2160 | DB37: =+AF37*CZ37/30*DA37 -> 30772.14 | DC37: =+DA37-DA38 -> 30
AG38: =+'[31]RES CUENTA'!$O$18 -> 14145.844 | CZ38: 0.03 | DA38: 2130 | DB38: =+AG38*CZ38/30*DA38 -> 30130.647 | DC38: =+DA38-DA39 -> 30
AH39: =+'[32]RES CUENTA'!$O$18 -> 14164.854 | CZ39: 0.03 | DA39: 2100 | DB39: =+AH39*CZ39/30*DA39 -> 29746.193 | DC39: =+DA39-DA40 -> 30
AI40: =+'[33]RES CUENTA'!$O$18 -> 18922.872 | CZ40: 0.03 | DA40: 2070 | DB40: =+AI40*CZ40/30*DA40 -> 39170.345 | DC40: =+DA40-DA41 -> 30
AJ41: =+'[34]RES CUENTA'!$O$18 -> 17793.58 | CZ41: 0.03 | DA41: 2040 | DB41: =+AJ41*CZ41/30*DA41 -> 36298.904 | DC41: =+DA41-DA42 -> 30
AK42: =+'[35]RES CUENTA'!$O$18 -> 17624.282 | CZ42: 0.03 | DA42: 2010 | DB42: =+AK42*CZ42/30*DA42 -> 35424.806 | DC42: =+DA42-DA43 -> 30
AL43: =+'[36]RES CUENTA'!$O$18 -> 17478.324 | CZ43: 0.03 | DA43: 1980 | DB43: =+AL43*CZ43/30*DA43 -> 34607.082 | DC43: =+DA43-DA44 -> 30
AM44: =+'[37]RES CUENTA'!$O$18 -> 20447.126 | CZ44: 0.03 | DA44: 1950 | DB44: =+AM44*CZ44/30*DA44 -> 39871.895 | DC44: =+DA44-DA45 -> 30
AN45: =+'[38]RES CUENTA'!$O$18 -> 19619.487 | CZ45: 0.03 | DA45: 1920 | DB45: =+AN45*CZ45/30*DA45 -> 37669.415 | DC45: =+DA45-DA46 -> 30
AO46: =+'[39]RES CUENTA'!$O$18 -> 20899.616 | CZ46: 0.03 | DA46: 1890 | DB46: =+AO46*CZ46/30*DA46 -> 39500.274 | DC46: =+DA46-DA47 -> 30
AP47: =+'[40]RES CUENTA'!$O$18 -> 19299.688 | CZ47: 0.03 | DA47: 1860 | DB47: =+AP47*CZ47/30*DA47 -> 35897.419 | DC47: =+DA47-DA48 -> 30
AQ48: =+'[41]RES CUENTA'!$O$18 -> 132770.99 | CZ48: 0.03 | DA48: 1830 | DB48: =+AQ48*CZ48/30*DA48 -> 242970.9 | DC48: =+DA48-DA49 -> 30
AR49: =+'[42]RES CUENTA'!$O$18 -> 24426.687 | CZ49: 0.03 | DA49: 1800 | DB49: =+AR49*CZ49/30*DA49 -> 43968.037 | DC49: =+DA49-DA50 -> 30
AS50: =+'[43]RES CUENTA'!$O$18 -> 28671.105 | CZ50: 0.03 | DA50: 1770 | DB50: =+AS50*CZ50/30*DA50 -> 50747.855 | DC50: =+DA50-DA51 -> 30
AT51: =+'[44]RES CUENTA'!$O$18 -> 22708.528 | CZ51: 0.03 | DA51: 1740 | DB51: =+AT51*CZ51/30*DA51 -> 39512.838 | DC51: =+DA51-DA52 -> 30
AU52: =+'[45]RES CUENTA'!$O$18 -> 23218.142 | CZ52: 0.03 | DA52: 1710 | DB52: =+AU52*CZ52/30*DA52 -> 39703.023 | DC52: =+DA52-DA53 -> 30
AV53: =+'[46]RES CUENTA'!$O$18 -> 26909.137 | CZ53: 0.03 | DA53: 1680 | DB53: =+AV53*CZ53/30*DA53 -> 45207.35 | DC53: =+DA53-DA54 -> 30
AW54: =+'[47]RES CUENTA'!$O$18 -> 28440.053 | CZ54: 0.03 | DA54: 1650 | DB54: =+AW54*CZ54/30*DA54 -> 46926.088 | DC54: =+DA54-DA55 -> 30
AX55: =+'[48]RES CUENTA'!$O$18 -> 30750.135 | CZ55: 0.03 | DA55: 1620 | DB55: =+AX55*CZ55/30*DA55 -> 49815.219 | DC55: =+DA55-DA56 -> 30
AY56: =+'[49]RES CUENTA'!$P$18 -> 28093.245 | CZ56: 0.03 | DA56: 1590 | DB56: =+AY56*CZ56/30*DA56 -> 44668.26 | DC56: =+DA56-DA57 -> 30
AZ57: =+'[50]RES CUENTA'!$P$18+111218 -> 143076.02 | CZ57: 0.03 | DA57: 1560 | DB57: =+AZ57*CZ57/30*DA57 -> 223198.6 | DC57: =+DA57-DA58 -> 30
BA58: =+'[51]RES CUENTA'!$Q$18 -> 35690.663 | CZ58: 0.03 | DA58: 1530 | DB58: =+BA58*CZ58/30*DA58 -> 54606.715 | DC58: =+DA58-DA59 -> 30
BB59: =+'[52]RES CUENTA'!$P$18 -> 26424.133 | CZ59: 0.03 | DA59: 1500 | DB59: =+BB59*CZ59/30*DA59 -> 39636.2 | DC59: =+DA59-DA60 -> 30
BC60: =+'[53]RES CUENTA'!$O$18 -> 39293.346 | CZ60: 0.03 | DA60: 1470 | DB60: =+BC60*CZ60/30*DA60 -> 57761.219 | DC60: =+DA60-DA61 -> 30
BD61: =+'[54]RES CUENTA'!$O$18 -> 38226.388 | CZ61: 0.03 | DA61: 1440 | DB61: =+BD61*CZ61/30*DA61 -> 55045.998 | DC61: =+DA61-DA62 -> 30
BE62: =+'[55]RES CUENTA'!$O$18 -> 40478.835 | CZ62: 0.03 | DA62: 1410 | DB62: =+BE62*CZ62/30*DA62 -> 57075.157 | DC62: =+DA62-DA63 -> 30
BF63: =+'[56]RES CUENTA'!$O$18 -> 52739.371 | CZ63: 0.03 | DA63: 1380 | DB63: =+BF63*CZ63/30*DA63 -> 72780.332 | DC63: =+DA63-DA64 -> 30
BG64: =+'[57]RES CUENTA'!$O$18 -> 51659.944 | CZ64: 0.03 | DA64: 1350 | DB64: =+BG64*CZ64/30*DA64 -> 69740.925 | DC64: =+DA64-DA65 -> 30
BH65: =+'[58]RES CUENTA'!$O$18 -> 57241.599 | CZ65: 0.03 | DA65: 1320 | DB65: =+BH65*CZ65/30*DA65 -> 75558.911 | DC65: =+DA65-DA66 -> 30
BI66: =+'[59]RES CUENTA'!$O$18 -> 62610.593 | CZ66: 0.03 | DA66: 1290 | DB66: =+BI66*CZ66/30*DA66 -> 80767.665 | DC66: =+DA66-DA67 -> 30
BJ67: =+'[60]RES CUENTA'!$O$18 -> 65096.384 | CZ67: 0.03 | DA67: 1260 | DB67: =+BJ67*CZ67/30*DA67 -> 82021.444 | DC67: =+DA67-DA68 -> 30
BK68: =+'[61]RES CUENTA'!$O$18 -> 71852.146 | CZ68: 0.03 | DA68: 1230 | DB68: =+BK68*CZ68/30*DA68 -> 88378.139 | DC68: =+DA68-DA69 -> 30
BL69: =+'[62]RES CUENTA'!$O$18 -> 68130.69 | CZ69: 0.03 | DA69: 1200 | DB69: =+BL69*CZ69/30*DA69 -> 81756.828 | DC69: =+DA69-DA70 -> 30
BM70: =+'[63]RES CUENTA'!$O$18 -> 78309.959 | CZ70: 0.03 | DA70: 1170 | DB70: =+BM70*CZ70/30*DA70 -> 91622.652 | DC70: =+DA70-DA71 -> 30
BN71: =+'[64]RES CUENTA'!$O$18 -> 82818.522 | CZ71: 0.03 | DA71: 1140 | DB71: =+BN71*CZ71/30*DA71 -> 94413.115 | DC71: =+DA71-DA72 -> 30
BO72: =+'[65]RES CUENTA'!$O$18 -> 88192.095 | CZ72: 0.03 | DA72: 1110 | DB72: =+BO72*CZ72/30*DA72 -> 97893.225 | DC72: =+DA72-DA73 -> 30
BP73: =+'[66]RES CUENTA'!$O$18 -> 89421.559 | CZ73: 0.03 | DA73: 1080 | DB73: =+BP73*CZ73/30*DA73 -> 96575.284 | DC73: =+DA73-DA74 -> 30
BQ74: =+'[67]RES CUENTA'!$O$18 -> 91567.417 | CZ74: 0.03 | DA74: 1050 | DB74: =+BQ74*CZ74/30*DA74 -> 96145.788 | DC74: =+DA74-DA75 -> 30
BR75: =+'[68]RES CUENTA'!$O$18 -> 92771.072 | CZ75: 0.03 | DA75: 1020 | DB75: =+BR75*CZ75/30*DA75 -> 94626.494 | DC75: =+DA75-DA76 -> 30
BS76: =+'[69]RES CUENTA'!$O$18 -> 96695.44 | CZ76: 0.03 | DA76: 990 | DB76: =+BS76*CZ76/30*DA76 -> 95728.485 | DC76: =+DA76-DA77 -> 30
BT77: =+'[70]RES CUENTA'!$O$18 -> 146163.14 | CZ77: 0.03 | DA77: 960 | DB77: =+BT77*CZ77/30*DA77 -> 140316.62 | DC77: =+DA77-DA78 -> 30
BU78: =+'[71]RES CUENTA'!$O$18 -> 146202.6 | CZ78: 0.03 | DA78: 930 | DB78: =+BU78*CZ78/30*DA78 -> 135968.42 | DC78: =+DA78-DA79 -> 30
BV79: =+'[72]RES CUENTA'!$O$18 -> 162604.16 | CZ79: 0.03 | DA79: 900 | DB79: =+BV79*CZ79/30*DA79 -> 146343.75 | DC79: =+DA79-DA80 -> 30
BW80: =+'[73]RES CUENTA'!$O$18 -> 156673.7 | CZ80: 0.03 | DA80: 870 | DB80: =+BW80*CZ80/30*DA80 -> 136306.12 | DC80: =+DA80-DA81 -> 30
BX81: =+'[74]RES CUENTA'!$O$18 -> 140587.83 | CZ81: 0.03 | DA81: 840 | DB81: =+BX81*CZ81/30*DA81 -> 118093.78 | DC81: =+DA81-DA82 -> 30
BY82: =+'[75]RES CUENTA'!$O$18 -> 184712.55 | CZ82: 0.03 | DA82: 810 | DB82: =+BY82*CZ82/30*DA82 -> 149617.17 | DC82: =+DA82-DA83 -> 30
BZ83: =+'[76]RES CUENTA'!$O$18 -> 176759.69 | CZ83: 0.03 | DA83: 780 | DB83: =+BZ83*CZ83/30*DA83 -> 137872.56 | DC83: =+DA83-DA84 -> 30
CA84: =+'[77]RES CUENTA'!$O$18 -> 307674.83 | CZ84: 0.03 | DA84: 750 | DB84: =CA84*CZ84/30*DA84 -> 230756.13 | DC84: =+DA84-DA85 -> 30
CB85: =+'[78]RES CUENTA'!$O$18 -> 363695.16 | CZ85: 0.03 | DA85: 720 | DB85: =CB85*CZ85/30*DA85 -> 261860.51 | DC85: =+DA85-DA86 -> 30
CC86: =+'[79]RES CUENTA'!$O$18 -> 321443.18 | CZ86: 0.03 | DA86: 690 | DB86: =CC86*CZ86/30*DA86 -> 221795.8 | DC86: =+DA86-DA87 -> 30
CD87: =+'[80]RES CUENTA'!$O$18 -> 297061.98 | CZ87: 0.03 | DA87: 660 | DB87: =CD87*CZ87/30*DA87 -> 196060.9 | DC87: =+DA87-DA88 -> 30
CE88: =+'[81]RES CUENTA'!$O$18 -> 344107.86 | CZ88: 0.03 | DA88: 630 | DB88: =CE88*CZ88/30*DA88 -> 216787.95 | DC88: =+DA88-DA89 -> 30
CF89: =+'[82]RES CUENTA'!$P$18 -> 342063.46 | CZ89: 0.03 | DA89: 600 | DB89: =CF89*CZ89/30*DA89 -> 205238.08 | DC89: =+DA89-DA90 -> 30
CG90: =+'[83]RES CUENTA'!$P$18 -> 399436.58 | CZ90: 0.03 | DA90: 570 | DB90: =CG90*CZ90/30*DA90 -> 227678.85 | DC90: =+DA90-DA91 -> 30
CH91: =+'[84]RES CUENTA'!$P$18 -> 417816.71 | CZ91: 0.03 | DA91: 540 | DB91: =CH91*CZ91/30*DA91 -> 225621.02 | DC91: =+DA91-DA92 -> 30
CI92: =+'[85]RES CUENTA'!$P$18 -> 439288.65 | CZ92: 0.03 | DA92: 510 | DB92: =CI92*CZ92/30*DA92 -> 224037.21 | DC92: =+DA92-DA93 -> 30
CJ93: =+'[86]RES CUENTA'!$P$18 -> 468794.54 | CZ93: 0.03 | DA93: 480 | DB93: =CJ93*CZ93/30*DA93 -> 225021.38 | DC93: =+DA93-DA94 -> 30
CK94: =+'[87]RES CUENTA'!$P$18 -> 459223.61 | CZ94: 0.03 | DA94: 450 | DB94: =CK94*CZ94/30*DA94 -> 206650.63 | DC94: =+DA94-DA95 -> 30
CL95: =+'[88]RES CUENTA'!$P$18 -> 466032.13 | CZ95: 0.03 | DA95: 420 | DB95: =CL95*CZ95/30*DA95 -> 195733.49 | DC95: =+DA95-DA96 -> 30
CM96: =+'[89]RES CUENTA'!$P$18 -> 538310.28 | CZ96: 0.03 | DA96: 390 | DB96: =CM96*CZ96/30*DA96 -> 209941.01 | DC96: =+DA96-DA97 -> 30
CN97: =+'[90]RES CUENTA'!$P$18 -> 590448.81 | CZ97: 0.03 | DA97: 360 | DB97: =CN97*CZ97/30*DA97 -> 212561.57 | DC97: =+DA97-DA98 -> 30
CO98: =+'[91]RES CUENTA'!$P$18 -> 645257.14 | CZ98: 0.03 | DA98: 330 | DB98: =CO98*CZ98/30*DA98 -> 212934.86 | DC98: =+DA98-DA99 -> 30
CP99: =+'[92]RES CUENTA'!$P$18 -> 676428.53 | CZ99: 0.03 | DA99: 300 | DB99: =CP99*CZ99/30*DA99 -> 202928.56 | DC99: =+DA99-DA100 -> 30
CQ100: =+'[93]RES CUENTA'!$P$18 -> 578025.61 | CZ100: 0.03 | DA100: 270 | DB100: =CQ100*CZ100/30*DA100 -> 156066.92 | DC100: =+DA100-DA101 -> 30
CR101: =+'[94]RES CUENTA'!$P$18 -> 690981.81 | CZ101: 0.03 | DA101: 240 | DB101: =CR101*CZ101/30*DA101 -> 165835.63 | DC101: =+DA101-DA102 -> 30
CS102: =+'[95]RES CUENTA'!$P$18 -> 692243.79 | CZ102: 0.03 | DA102: 210 | DB102: =CS102*CZ102/30*DA102 -> 145371.2 | DC102: =+DA102-DA103 -> 30
CT103: =+'[96]RES CUENTA'!$P$18 -> 795467.28 | CZ103: 0.03 | DA103: 180 | DB103: =CT103*CZ103/30*DA103 -> 143184.11 | DC103: =+DA103-DA104 -> 30
CU104: =+'[97]RES CUENTA'!$P$18 -> 705283.23 | CZ104: 0.03 | DA104: 150 | DB104: =CU104*CZ104/30*DA104 -> 105792.48 | DC104: =+DA104-DA105 -> 30
CV105: =+'[98]RES CUENTA'!$P$18 -> 705355.96 | CZ105: 0.03 | DA105: 120 | DB105: =CV105*CZ105/30*DA105 -> 84642.715 | DC105: =+DA105-DA106 -> 30
CW106: =+'[99]RES CUENTA'!$P$18 -> 657036.45 | CZ106: 0.03 | DA106: 90 | DB106: =CW106*CZ106/30*DA106 -> 59133.28 | DC106: =+DA106-DA107 -> 30
...

Sheet SUELDO
A2: EMPLEADOR: CONS. DE PROP. BERUTI 4575/77 | F2: CUIT: 30-70807291-1
A3: Domicilio: Beruti 4575/77 | F3: Recibo: 1 ORIGINAL
B4: 1425 - Capital Federal | F4: Cuil: 23-11424220-9
A5: PERIODO | B5: APELLIDO Y NOMBRES | F5: Categoria | G5: Legajo
A6: 37653 | B6: OSUNA CLAUDIO R. | F6: 0-03 | G6: 1
A7: BANCO | B7: PERIODO DEPOSITADO | E7: FECHA | F7: TAREA | G7: INGRESO
A8: Nación | B8: Febrero 2003 | E8: 37687 | F8: Enc.Perm c/viv | G8: 37518
A9: CONCEPTOS | E9: UNIDADES | F9: REMUNERAC. | G9: DESCUENT.
A11: BASICO | F11: =374.4 -> 374.4 | I11: feriados,dom
A12: RETIRO DE RESIDUOS | E12: 15 | F12: =+E12*1.26 -> 18.9 | I12: 6
A13: PLUS JARDIN | F13: =16.98 -> 16.98 | I13: 5 | J13: DIAS
A14: PLUS COCHERA | F14: =16.98 -> 16.98 | I14: =+I12*I13 -> 30
A15: DEC.2641/02 | F15: 150 | I15: GRATIFICACION | O15: =+H17+109.74 -> 1832.43
A16: RET. JUBILACION | C16: 7 | D16: % | F16: - | G16: =+$H$17*C16/100 -> 120.5883 | I16: DS NORMALES | K16: 1 | L16: =427.26/30*1 -> 14.242
A17: LEY N 19032 | C17: 3 | D17: % | F17: - | G17: =+$H$17*C17/100 -> 51.6807 | H17: =895.36+727.33+100 -> 1722.69 | I17: HS EXTRAS | K17: 24 | L17: =427.26/200*2*24 -> 102.5424
A18: OBRA SOCIAL | C18: 2.7 | D18: % | F18: - | G18: =+$H$17*C18/100 -> 46.51263 | L18: =+L16+L17 -> 116.7844
A19: ANSSAL | C19: 0.3 | D19: % | F19: - | G19: =+$H$17*C19/100 -> 5.16807 | H19: =SUM(G16:G19) -> 223.9497
A20: CUOTA SINDICAL | C20: 2 | D20: % | F20: - | G20: =+$H$17*C20/100 -> 34.4538 | H20: =59.38+8.76+25.92+5.2+3.5+31.53 -> 134.29 | I20: SETIEMBRE
A21: CAJA PROT FAMILIA | C21: 1 | D21: % | F21: - | G21: =+$H$17*C21/100 -> 17.2269 | H21: =134.29/583.86 -> 0.23000377 | I21: DS NORMALES | K21: 2.5 | L21: =427.26/30*2.5 -> 35.605
H22: =+H21*H17 -> 396.22519 | I22: HS EXTRAS | K22: 40 | L22: =427.26/200*2*40 -> 170.904
D23: TOTAL BRUTO | F23: =SUM(F11:F22) -> 577.26 | H23: =+H22+H19 -> 620.17489
D24: TOTAL DESCUENTOS | F24: - | G24: =SUM(G16:G22) -> 275.6304
D25: TOTAL NETO | F25: - | G25: =+F23-G24 -> 301.6296
D26: REDONDEO | F26: - | G26: =ROUND(G25,0) -> 302
D27: SON PESOS:
A28: FIRMA DEL EMPLEADO | D28: SEICIENTOS OCHENTA Y OCHO
A29: Recibí de la firma cuyo rubro se indica arriba el importe neto de esta liquidación en pago de mi
A30: remuneración correspondiente al período indicado y duplicado de la misma.
A35: EMPLEADOR: CONS. DE PROP. BERUTI 4575/77 | F35: CUIT: 30-70807291-1
A36: Domicilio: Beruti 4575/77 | F36: Recibo: 2 DUPLICADO
B37: 1425 - Capital Federal | F37: Cuil: 23-11424220-9
A38: PERIODO | B38: APELLIDO Y NOMBRES | F38: Categoria | G38: Legajo
A39: =+A6 -> 37653 | B39: OSUNA CLAUDIO R. | F39: 0-03 | G39: 1
A40: BANCO | B40: PERIODO DEPOSITADO | E40: FECHA | F40: TAREA | G40: INGRESO
A41: Nación | B41: Febrero 2003 | E41: =+E8 -> 37687 | F41: Enc.Perm c/viv | G41: 37518
A42: CONCEPTOS | E42: UNIDADES | F42: REMUNERAC. | G42: DESCUENT.
A44: BASICO | F44: =374.4 -> 374.4
A45: HORAS EXTRAS 100% | E45: =3+3+8+3+8+3+8+3+8 -> 47 | F45: =+#REF! -> #REF!
A46: =+#REF! -> #REF! | E46: =+#REF! -> #REF! | F46: =+#REF! -> #REF!
A47: RETIRO DE RESIDUOS | E47: 15 | F47: =+E47*1.26 -> 18.9
A48: PLUS JARDIN | F48: =16.98 -> 16.98
A49: PLUS COCHERA | F49: =16.98 -> 16.98
A50: DEC.2641/02 | F50: =+F15 -> 150
A51: RET. JUBILACION | C51: 7 | D51: % | F51: - | G51: =+$H$17*C51/100 -> 120.5883
A52: LEY Nº 19032 | C52: 3 | D52: % | F52: - | G52: =+$H$17*C52/100 -> 51.6807 | H52: =+G52+G51 -> 172.269 | I52: =+G51+G52 -> 172.269
A53: OBRA SOCIAL | C53: 2.7 | D53: % | F53: - | G53: =+$H$17*C53/100 -> 46.51263 | H53: =+H52+G54 -> 177.43707
A54: ANSSAL | C54: 0.3 | D54: % | F54: - | G54: =+$H$17*C54/100 -> 5.16807 | K54: ENCARGADO | L54: =+LIQ!E21 -> 1013447.2
A55: CUOTA SINDICAL | C55: 2 | D55: % | F55: - | G55: =+$H$17*C55/100 -> 34.4538 | K55: SUPLENTE | L55: 0
A56: CAJA PROT FAMILIA | C56: 1 | D56: % | F56: - | G56: =+$H$17*C56/100 -> 17.2269 | L56: =SUM(L54:L55) -> 1013447.2
K57: =12066.3+6515.8 -> 18582.1 | L57: 0.75 | M57: =+K59*L57/100 -> 7600.854
D58: TOTAL BRUTO | F58: =SUM(F44:F57) -> #REF! | I58: Sindicato suterh | L58: =0.75 -> 0.75 | M58: =+K59*L58/100 -> 7600.854
D59: TOTAL DESCUENTOS | F59: - | G59: =SUM(G51:G57) -> 275.6304 | I59: =+K59*J59 -> 15201.708 | J59: 0.015 | K59: =+L56 -> 1013447.2 | L59: 0.04 | M59: =+N59*L59 -> 40537.888 | N59: =+K59 -> 1013447.2 | O59: 0.005 | Q59: =+O59*0.02 -> 0.0001 | R59: =+O59*0.01 -> 5e-05 | S59: =+R59+Q59 -> 0.00015
D60: TOTAL NETO | F60: - | G60: =+F58-G59 -> #REF! | I60: =+L54*0.03+L55*0.01 -> 30403.416 | J60: =3/100 -> 0.03 | L60: 0.01 | M60: =+N59*L60 -> 10134.472 | Q60: =+O60*0.02 -> 0 | R60: =+O60*0.01 -> 0 | S60: =+R60+Q60 -> 0
D61: REDONDEO | F61: - | G61: =ROUND(G60,0) -> #REF! | I61: =+I59+I60+0.01 -> 45605.134 | M61: =SUM(M57:M60) -> 65874.068 | O61: =+K59*O59 -> 5067.236 | Q61: =+Q60+Q59 -> 0.0001 | R61: =+R60+R59 -> 5e-05 | S61: =+Q61+R61 -> 0.00015
D62: SON PESOS:
A63: FIRMA DEL EMPLEADOR | D63: =+D28 -> SEICIENTOS OCHENTA Y OCHO | I63: art
A64: Recibí de la firma cuyo rubro se indica arriba el importe neto de esta liquidación en pago de mi | I64: fija | J64: 0.6 | K64: 0.6
A65: remuneración correspondiente al período indicado y duplicado de la misma.
I66: porcenta | J66: 0.028 | K66: =+K59*0.028 -> 28376.522
I67: por empleado | K67: =+K66+K64 -> 28377.122
J69: =42.15/1881.8 -> 0.022398767

Sheet RECIBOS (2)
B1: =+LIQ!H1 -> 46143 | D1: 46188 | E1: Lima 461 C:A:B:A: | F1: P/Depósito/transferencia en Bco Santander Rio
B2: =+'RES CUENTA'!D15 -> Casa Lopez | C2: =+'RES CUENTA'!G15 -> 17.08 | D2: =+'RES CUENTA'!B15 -> 1 | E2: =+'RES CUENTA'!H15 -> 0 | F2: Cta. Cte. $ N° 210-1950/3 | H2: 210-1950/3
B3: =+'RES CUENTA'!D16 -> Eduardo Sanchez | C3: =+'RES CUENTA'!G16 -> 17.08 | D3: =+'RES CUENTA'!B16 -> 2 | E3: =+'RES CUENTA'!H16 -> 0 | F3: CBU 0720210220000000195036
B4: =+'RES CUENTA'!D17 -> Benjamin Fernandez | C4: =+'RES CUENTA'!G17 -> 8.19 | D4: =+'RES CUENTA'!B17 -> 3 | E4: =+'RES CUENTA'!H17 -> 12.44 | F4: =+LIQ!G4 -> CUIT: 30-53267348-4
B5: =+'RES CUENTA'!D18 -> Franco Lippi | C5: =+'RES CUENTA'!G18 -> 8.19 | D5: =+'RES CUENTA'!B18 -> 4 | E5: =+'RES CUENTA'!H18 -> 12.44
B6: =+'RES CUENTA'!D19 -> Antonella Denegri | C6: =+'RES CUENTA'!G19 -> 8.27 | D6: =+'RES CUENTA'!B19 -> 5 | E6: =+'RES CUENTA'!H19 -> 12.56
B7: =+'RES CUENTA'!D20 -> Ana Isabel Pirro | C7: =+'RES CUENTA'!G20 -> 8.27 | D7: =+'RES CUENTA'!B20 -> 6 | E7: =+'RES CUENTA'!H20 -> 12.56
B8: =+'RES CUENTA'!D21 -> Leandro Acero | C8: =+'RES CUENTA'!G21 -> 8.35 | D8: =+'RES CUENTA'!B21 -> 7 | E8: =+'RES CUENTA'!H21 -> 12.68
B9: =+'RES CUENTA'!D22 -> Jose A. Montans | C9: =+'RES CUENTA'!G22 -> 8.35 | D9: =+'RES CUENTA'!B22 -> 8 | E9: =+'RES CUENTA'!H22 -> 12.68
B10: =+'RES CUENTA'!D23 -> Miguel A. Machinandiarena | C10: =+'RES CUENTA'!G23 -> 8.11 | D10: =+'RES CUENTA'!B23 -> 9 | E10: =+'RES CUENTA'!H23 -> 12.32
B11: =+'RES CUENTA'!D24 -> Olivier Liem | C11: =+'RES CUENTA'!G24 -> 8.11 | D11: =+'RES CUENTA'!B24 -> 10 | E11: =+'RES CUENTA'!H24 -> 12.32
B12: =+'RES CUENTA'!#REF! -> #REF! | C12: =+'RES CUENTA'!#REF! -> #REF! | D12: =+'RES CUENTA'!#REF! -> #REF! | E12: =+'RES CUENTA'!#REF! -> #REF!
B13: =+'RES CUENTA'!#REF! -> #REF! | C13: =+'RES CUENTA'!#REF! -> #REF! | D13: =+'RES CUENTA'!#REF! -> #REF! | E13: =+'RES CUENTA'!#REF! -> #REF!
B14: =+'RES CUENTA'!#REF! -> #REF! | C14: =+'RES CUENTA'!#REF! -> #REF! | D14: =+'RES CUENTA'!#REF! -> #REF! | E14: =+'RES CUENTA'!#REF! -> #REF!
B15: =+'RES CUENTA'!#REF! -> #REF! | C15: =+'RES CUENTA'!#REF! -> #REF! | D15: =+'RES CUENTA'!#REF! -> #REF! | E15: =+'RES CUENTA'!#REF! -> #REF!
B16: =+'RES CUENTA'!#REF! -> #REF! | C16: =+'RES CUENTA'!#REF! -> #REF! | D16: =+'RES CUENTA'!#REF! -> #REF! | E16: =+'RES CUENTA'!#REF! -> #REF!
B17: =+'RES CUENTA'!#REF! -> #REF! | C17: =+'RES CUENTA'!#REF! -> #REF! | D17: =+'RES CUENTA'!#REF! -> #REF! | E17: =+'RES CUENTA'!#REF! -> #REF!
B18: =+'RES CUENTA'!#REF! -> #REF! | C18: =+'RES CUENTA'!#REF! -> #REF! | D18: =+'RES CUENTA'!#REF! -> #REF! | E18: =+'RES CUENTA'!#REF! -> #REF!
B19: =+'RES CUENTA'!#REF! -> #REF! | C19: =+'RES CUENTA'!#REF! -> #REF! | D19: =+'RES CUENTA'!#REF! -> #REF! | E19: =+'RES CUENTA'!#REF! -> #REF!
B20: =+'RES CUENTA'!#REF! -> #REF! | C20: =+'RES CUENTA'!#REF! -> #REF! | D20: =+'RES CUENTA'!#REF! -> #REF! | E20: =+'RES CUENTA'!#REF! -> #REF!
B21: =+'RES CUENTA'!#REF! -> #REF! | C21: =+'RES CUENTA'!#REF! -> #REF! | D21: =+'RES CUENTA'!#REF! -> #REF! | E21: =+'RES CUENTA'!#REF! -> #REF!
B22: =+'RES CUENTA'!#REF! -> #REF! | C22: =+'RES CUENTA'!#REF! -> #REF! | D22: =+'RES CUENTA'!#REF! -> #REF! | E22: =+'RES CUENTA'!#REF! -> #REF!
B23: =+'RES CUENTA'!#REF! -> #REF! | C23: =+'RES CUENTA'!#REF! -> #REF! | D23: =+'RES CUENTA'!#REF! -> #REF! | E23: =+'RES CUENTA'!#REF! -> #REF!
B24: =+'RES CUENTA'!#REF! -> #REF! | C24: =+'RES CUENTA'!#REF! -> #REF! | D24: =+'RES CUENTA'!#REF! -> #REF! | E24: =+'RES CUENTA'!#REF! -> #REF!
C25: =SUM(C2:C24) -> #REF! | E25: =SUM(E2:E24) -> #REF!
E30: =+$B$1 -> 46143 | G30: =+$D$1 -> 46188
B34: =+B2 -> Casa Lopez | E34: =+E1 -> Lima 461 C:A:B:A: | H34: Unid. 1
H35: =+'RES CUENTA'!A15 -> Local
B38: Expensas Gastos A | D38: =+'RES CUENTA'!L25 -> 10859801 | E38: =+'RES CUENTA'!G15 -> 17.08 | F38: =+D38*E38/100 -> 1854854.1
B39: Cable | D39: 0 | E39: 0 | F39: =+D39*E39/100 -> 0
B40: Cuota extra | D40: 0 | E40: 0 | F40: 0
B41: Deuda Anterior | D41: =+'RES CUENTA'!Q15 -> 16679327 | E41: 0 | F41: =+D41 -> 16679327
B42: Intereses | D42: =+'RES CUENTA'!R15 -> 8967099.7 | E42: 0 | F42: =+D42+E42 -> 8967099.7
F43: =SUM(F38:F42) -> 27501281
B49: =+B2 -> Casa Lopez | E49: =+B2 -> Casa Lopez
B51: =+E1 -> Lima 461 C:A:B:A: | D51: =+H34 -> Unid. 1 | E51: =+E1 -> Lima 461 C:A:B:A: | H51: =+D51 -> Unid. 1
D52: =+H52 -> Local | H52: =+H35 -> Local
B54: =+F1 -> P/Depósito/transferencia en Bco Santander Rio
B55: =+F2 -> Cta. Cte. $ N° 210-1950/3
B56: =+F3 -> CBU 0720210220000000195036 | E56: G A | F56: =+F38 -> 1854854.1 | H56: =+D1 -> 46188
B57: =+F4 -> CUIT: 30-53267348-4 | E57: G E | F57: =+F39 -> 0
E58: D A | F58: =+F41 -> 16679327
E59: INT | F59: =+F42 -> 8967099.7
E60: OTROS | F60: =+F40 -> 0
B61: =+$G$30 -> 46188 | C61: =+F43 -> 27501281 | E61: TOT | F61: =+F43 -> 27501281
E70: =+$B$1 -> 46143 | G70: =+$D$1 -> 46188
B73: =+B3 -> Eduardo Sanchez | E73: =+E1 -> Lima 461 C:A:B:A: | H73: Unid. 2
H74: =+'RES CUENTA'!A16 -> Local
B77: Expensas Gastos A | D77: =+'RES CUENTA'!L25 -> 10859801 | E77: =+'RES CUENTA'!G16 -> 17.08 | F77: =+D77*E77/100 -> 1854854.1
B78: Cable | D78: =+'RES CUENTA'!N16 -> 0 | E78: 0 | F78: =+D78 -> 0
B79: Cuota extra | D79: 0 | E79: 0 | F79: 0
B80: Deuda Anterior | D80: =+'RES CUENTA'!Q16 -> 0 | E80: 0 | F80: =+D80 -> 0
B81: Intereses | D81: =+'RES CUENTA'!R16 -> 0 | E81: 0 | F81: =+'RES CUENTA'!R16 -> 0
F82: =SUM(F77:F81) -> 1854854.1
B88: =+B73 -> Eduardo Sanchez | E88: =+B73 -> Eduardo Sanchez
H89: =+D90 -> Unid. 2
B90: =+E1 -> Lima 461 C:A:B:A: | D90: Unid. 2 | E90: =+E1 -> Lima 461 C:A:B:A: | H90: =+H74 -> Local
D91: =+H74 -> Local
B93: =+F1 -> P/Depósito/transferencia en Bco Santander Rio
B94: =+F2 -> Cta. Cte. $ N° 210-1950/3
B95: =+F3 -> CBU 0720210220000000195036 | E95: G A y B | F95: =+F77 -> 1854854.1 | H95: =+D1 -> 46188
B96: =+F4 -> CUIT: 30-53267348-4 | E96: G E | F96: =+F78 -> 0
E97: D A | F97: =+F80 -> 0
E98: INT | F98: =+'RES CUENTA'!R16 -> 0
E99: OTROS | F99: =+F79 -> 0
B100: =+$G$30 -> 46188 | C100: =+F82 -> 1854854.1 | E100: TOT | F100: =+F82 -> 1854854.1
E107: =+$B$1 -> 46143 | G107: =+$D$1 -> 46188
B111: =+B4 -> Benjamin Fernandez | E111: =+E34 -> Lima 461 C:A:B:A: | H111: Unid. 3
H112: =+'RES CUENTA'!A17 -> 1A
B115: Expensas Gastos A | D115: =+'RES CUENTA'!L25 -> 10859801 | E115: =+'RES CUENTA'!G17 -> 8.19 | F115: =+D115*E115/100 -> 889417.74
B116: Expensas Gastos B | D116: =+'RES CUENTA'!M25 -> 125000 | E116: =+'RES CUENTA'!H17 -> 12.44 | F116: =+D116*E116/100 -> 15550
B117: Cable | D117: =+'RES CUENTA'!N17 -> 0 | E117: 0 | F117: =+D117 -> 0
B118: Cuota extra | D118: 0 | E118: 0 | F118: 0
B119: Deuda Anterior | D119: =+'RES CUENTA'!Q17 -> -29700 | E119: 0 | F119: =+D119 -> -29700
B120: Intereses | D120: =+'RES CUENTA'!R17 -> 0 | E120: 0 | F120: =+D120 -> 0
F121: =SUM(F115:F120) -> 875267.74
B127: =+B111 -> Benjamin Fernandez | E127: =+B127 -> Benjamin Fernandez
B129: =+E1 -> Lima 461 C:A:B:A: | D129: =+H111 -> Unid. 3 | E129: =+E1 -> Lima 461 C:A:B:A: | H129: =+D129 -> Unid. 3
D130: =+H130 -> 1A | H130: =+H112 -> 1A
B132: =+F1 -> P/Depósito/transferencia en Bco Santander Rio
B133: =+F2 -> Cta. Cte. $ N° 210-1950/3
B134: =+F3 -> CBU 0720210220000000195036 | E134: G A | F134: =+F115 -> 889417.74 | H134: =+D1 -> 46188
B135: =+F4 -> CUIT: 30-53267348-4 | E135: G B | F135: =+F116 -> 15550
E136: D A | F136: =+F119 -> -29700
E137: INT | F137: =+'RES CUENTA'!R17 -> 0
E138: OTROS | F138: =+F117+F118 -> 0
B139: =+$G$30 -> 46188 | C139: =+F121 -> 875267.74 | E139: TOT | F139: =+F121 -> 875267.74
E149: =+$B$1 -> 46143 | G149: =+$D$1 -> 46188
B152: =+B5 -> Franco Lippi | E152: =+E1 -> Lima 461 C:A:B:A: | H152: Unid. 4
H153: =+'RES CUENTA'!A18 -> 1B
B156: Expensas Gastos A | D156: =+'RES CUENTA'!L25 -> 10859801 | E156: =+'RES CUENTA'!G18 -> 8.19 | F156: =+D156*E156/100 -> 889417.74
B157: Expensas Gastos B | D157: =+'RES CUENTA'!M25 -> 125000 | E157: =+'RES CUENTA'!H18 -> 12.44 | F157: =+D157*E157/100 -> 15550
B158: Cable | D158: =+'RES CUENTA'!N18 -> 0 | E158: 0 | F158: =+D158 -> 0
B159: Cuota extra | D159: 0 | E159: 0 | F159: 0
B160: Deuda Anterior | D160: =+'RES CUENTA'!Q18 -> 0 | E160: 0 | F160: =+D160 -> 0
B161: Intereses | D161: =+'RES CUENTA'!R18 -> 0 | E161: 0 | F161: =+D161 -> 0
F162: =SUM(F156:F161) -> 904967.74
B167: =+B152 -> Franco Lippi | E167: =+B152 -> Franco Lippi
H168: Unid. 4
B169: =+E1 -> Lima 461 C:A:B:A: | D169: Unid. 4 | E169: =+E1 -> Lima 461 C:A:B:A: | H169: =+H153 -> 1B
...

Sheet RECIBOS
B1: =+LIQ!H1 -> 46143 | D1: 46037 | E1: Lima 461 C:A:B:A: | F1: P/Depósito/transferencia en Bco Santander Rio
B2: =+'RES CUENTA'!D15 -> Casa Lopez | C2: =+'RES CUENTA'!G15 -> 17.08 | D2: =+'RES CUENTA'!B15 -> 1 | E2: =+'RES CUENTA'!H15 -> 0 | F2: Cta. Cte. $ N° 210-1950/3 | H2: 210-1950/3
B3: =+'RES CUENTA'!D16 -> Eduardo Sanchez | C3: =+'RES CUENTA'!G16 -> 17.08 | D3: =+'RES CUENTA'!B16 -> 2 | E3: =+'RES CUENTA'!H16 -> 0 | F3: CBU 0720210220000000195036
B4: =+'RES CUENTA'!D17 -> Benjamin Fernandez | C4: =+'RES CUENTA'!G17 -> 8.19 | D4: =+'RES CUENTA'!B17 -> 3 | E4: =+'RES CUENTA'!H17 -> 12.44 | F4: =+LIQ!G4 -> CUIT: 30-53267348-4
B5: =+'RES CUENTA'!D18 -> Franco Lippi | C5: =+'RES CUENTA'!G18 -> 8.19 | D5: =+'RES CUENTA'!B18 -> 4 | E5: =+'RES CUENTA'!H18 -> 12.44
B6: =+'RES CUENTA'!D19 -> Antonella Denegri | C6: =+'RES CUENTA'!G19 -> 8.27 | D6: =+'RES CUENTA'!B19 -> 5 | E6: =+'RES CUENTA'!H19 -> 12.56
B7: =+'RES CUENTA'!D20 -> Ana Isabel Pirro | C7: =+'RES CUENTA'!G20 -> 8.27 | D7: =+'RES CUENTA'!B20 -> 6 | E7: =+'RES CUENTA'!H20 -> 12.56
B8: =+'RES CUENTA'!D21 -> Leandro Acero | C8: =+'RES CUENTA'!G21 -> 8.35 | D8: =+'RES CUENTA'!B21 -> 7 | E8: =+'RES CUENTA'!H21 -> 12.68
B9: =+'RES CUENTA'!D22 -> Jose A. Montans | C9: =+'RES CUENTA'!G22 -> 8.35 | D9: =+'RES CUENTA'!B22 -> 8 | E9: =+'RES CUENTA'!H22 -> 12.68
B10: =+'RES CUENTA'!D23 -> Miguel A. Machinandiarena | C10: =+'RES CUENTA'!G23 -> 8.11 | D10: =+'RES CUENTA'!B23 -> 9 | E10: =+'RES CUENTA'!H23 -> 12.32
B11: =+'RES CUENTA'!D24 -> Olivier Liem | C11: =+'RES CUENTA'!G24 -> 8.11 | D11: =+'RES CUENTA'!B24 -> 10 | E11: =+'RES CUENTA'!H24 -> 12.32
B12: =+'RES CUENTA'!#REF! -> #REF! | C12: =+'RES CUENTA'!#REF! -> #REF! | D12: =+'RES CUENTA'!#REF! -> #REF! | E12: =+'RES CUENTA'!#REF! -> #REF!
B13: =+'RES CUENTA'!#REF! -> #REF! | C13: =+'RES CUENTA'!#REF! -> #REF! | D13: =+'RES CUENTA'!#REF! -> #REF! | E13: =+'RES CUENTA'!#REF! -> #REF!
B14: =+'RES CUENTA'!#REF! -> #REF! | C14: =+'RES CUENTA'!#REF! -> #REF! | D14: =+'RES CUENTA'!#REF! -> #REF! | E14: =+'RES CUENTA'!#REF! -> #REF!
B15: =+'RES CUENTA'!#REF! -> #REF! | C15: =+'RES CUENTA'!#REF! -> #REF! | D15: =+'RES CUENTA'!#REF! -> #REF! | E15: =+'RES CUENTA'!#REF! -> #REF!
B16: =+'RES CUENTA'!#REF! -> #REF! | C16: =+'RES CUENTA'!#REF! -> #REF! | D16: =+'RES CUENTA'!#REF! -> #REF! | E16: =+'RES CUENTA'!#REF! -> #REF!
B17: =+'RES CUENTA'!#REF! -> #REF! | C17: =+'RES CUENTA'!#REF! -> #REF! | D17: =+'RES CUENTA'!#REF! -> #REF! | E17: =+'RES CUENTA'!#REF! -> #REF!
B18: =+'RES CUENTA'!#REF! -> #REF! | C18: =+'RES CUENTA'!#REF! -> #REF! | D18: =+'RES CUENTA'!#REF! -> #REF! | E18: =+'RES CUENTA'!#REF! -> #REF!
B19: =+'RES CUENTA'!#REF! -> #REF! | C19: =+'RES CUENTA'!#REF! -> #REF! | D19: =+'RES CUENTA'!#REF! -> #REF! | E19: =+'RES CUENTA'!#REF! -> #REF!
B20: =+'RES CUENTA'!#REF! -> #REF! | C20: =+'RES CUENTA'!#REF! -> #REF! | D20: =+'RES CUENTA'!#REF! -> #REF! | E20: =+'RES CUENTA'!#REF! -> #REF!
B21: =+'RES CUENTA'!#REF! -> #REF! | C21: =+'RES CUENTA'!#REF! -> #REF! | D21: =+'RES CUENTA'!#REF! -> #REF! | E21: =+'RES CUENTA'!#REF! -> #REF!
B22: =+'RES CUENTA'!#REF! -> #REF! | C22: =+'RES CUENTA'!#REF! -> #REF! | D22: =+'RES CUENTA'!#REF! -> #REF! | E22: =+'RES CUENTA'!#REF! -> #REF!
B23: =+'RES CUENTA'!#REF! -> #REF! | C23: =+'RES CUENTA'!#REF! -> #REF! | D23: =+'RES CUENTA'!#REF! -> #REF! | E23: =+'RES CUENTA'!#REF! -> #REF!
B24: =+'RES CUENTA'!#REF! -> #REF! | C24: =+'RES CUENTA'!#REF! -> #REF! | D24: =+'RES CUENTA'!#REF! -> #REF! | E24: =+'RES CUENTA'!#REF! -> #REF!
C25: =SUM(C2:C24) -> #REF! | E25: =SUM(E2:E24) -> #REF!
E30: =+$B$1 -> 46143 | G30: =+$D$1 -> 46037
B34: =+B2 -> Casa Lopez | E34: =+E1 -> Lima 461 C:A:B:A: | H34: Unid. 1
H35: =+'RES CUENTA'!A15 -> Local
B38: Expensas Gastos A | D38: =+'RES CUENTA'!L25 -> 10859801 | E38: =+'RES CUENTA'!G15 -> 17.08 | F38: =+D38*E38/100 -> 1854854.1
B39: Cable | D39: 0 | E39: 0 | F39: =+D39*E39/100 -> 0
B40: Cuota extra | D40: 0 | E40: 0 | F40: 0
B41: Deuda Anterior | D41: =+'RES CUENTA'!Q15 -> 16679327 | E41: 0 | F41: =+D41 -> 16679327
B42: Intereses | D42: =+'RES CUENTA'!R15 -> 8967099.7 | E42: 0 | F42: =+D42+E42 -> 8967099.7
F43: =SUM(F38:F42) -> 27501281
B49: =+B2 -> Casa Lopez | E49: =+B2 -> Casa Lopez
B51: =+E1 -> Lima 461 C:A:B:A: | D51: =+H34 -> Unid. 1 | E51: =+E1 -> Lima 461 C:A:B:A: | H51: =+D51 -> Unid. 1
D52: =+H52 -> Local | H52: =+H35 -> Local
B54: =+F1 -> P/Depósito/transferencia en Bco Santander Rio
B55: =+F2 -> Cta. Cte. $ N° 210-1950/3
B56: =+F3 -> CBU 0720210220000000195036 | E56: G A | F56: =+F38 -> 1854854.1 | H56: =+D1 -> 46037
B57: =+F4 -> CUIT: 30-53267348-4 | E57: G E | F57: =+F39 -> 0
E58: D A | F58: =+F41 -> 16679327
E59: INT | F59: =+F42 -> 8967099.7
E60: OTROS | F60: =+F40 -> 0
B61: =+$G$30 -> 46037 | C61: =+F43 -> 27501281 | E61: TOT | F61: =+F43 -> 27501281
E70: =+$B$1 -> 46143 | G70: =+$D$1 -> 46037
B73: =+B3 -> Eduardo Sanchez | E73: =+E1 -> Lima 461 C:A:B:A: | H73: Unid. 2
H74: =+'RES CUENTA'!A16 -> Local
B77: Expensas Gastos A | D77: =+'RES CUENTA'!L25 -> 10859801 | E77: =+'RES CUENTA'!G16 -> 17.08 | F77: =+D77*E77/100 -> 1854854.1
B78: Cable | D78: =+'RES CUENTA'!N16 -> 0 | E78: 0 | F78: =+D78 -> 0
B79: Cuota extra | D79: 0 | E79: 0 | F79: 0
B80: Deuda Anterior | D80: =+'RES CUENTA'!Q16 -> 0 | E80: 0 | F80: =+D80 -> 0
B81: Intereses | D81: =+'RES CUENTA'!R16 -> 0 | E81: 0 | F81: =+'RES CUENTA'!R16 -> 0
F82: =SUM(F77:F81) -> 1854854.1
B88: =+B73 -> Eduardo Sanchez | E88: =+B73 -> Eduardo Sanchez
H89: =+D90 -> Unid. 2
B90: =+E1 -> Lima 461 C:A:B:A: | D90: Unid. 2 | E90: =+E1 -> Lima 461 C:A:B:A: | H90: =+H74 -> Local
D91: =+H74 -> Local
B93: =+F1 -> P/Depósito/transferencia en Bco Santander Rio
B94: =+F2 -> Cta. Cte. $ N° 210-1950/3
B95: =+F3 -> CBU 0720210220000000195036 | E95: G A y B | F95: =+F77 -> 1854854.1 | H95: =+D1 -> 46037
B96: =+F4 -> CUIT: 30-53267348-4 | E96: G E | F96: =+F78 -> 0
E97: D A | F97: =+F80 -> 0
E98: INT | F98: =+'RES CUENTA'!R16 -> 0
E99: OTROS | F99: =+F79 -> 0
B100: =+$G$30 -> 46037 | C100: =+F82 -> 1854854.1 | E100: TOT | F100: =+F82 -> 1854854.1
E107: =+$B$1 -> 46143 | G107: =+$D$1 -> 46037
B111: =+B4 -> Benjamin Fernandez | E111: =+E34 -> Lima 461 C:A:B:A: | H111: Unid. 3
H112: =+'RES CUENTA'!A17 -> 1A
B115: Expensas Gastos A | D115: =+'RES CUENTA'!L25 -> 10859801 | E115: =+'RES CUENTA'!G17 -> 8.19 | F115: =+D115*E115/100 -> 889417.74
B116: Expensas Gastos B | D116: =+'RES CUENTA'!M25 -> 125000 | E116: =+'RES CUENTA'!H17 -> 12.44 | F116: =+D116*E116/100 -> 15550
B117: Cable | D117: =+'RES CUENTA'!N17 -> 0 | E117: 0 | F117: =+D117 -> 0
B118: Cuota extra | D118: 0 | E118: 0 | F118: 0
B119: Deuda Anterior | D119: =+'RES CUENTA'!Q17 -> -29700 | E119: 0 | F119: =+D119 -> -29700
B120: Intereses | D120: =+'RES CUENTA'!R17 -> 0 | E120: 0 | F120: =+D120 -> 0
F121: =SUM(F115:F120) -> 875267.74
B127: =+B111 -> Benjamin Fernandez | E127: =+B127 -> Benjamin Fernandez
B129: =+E1 -> Lima 461 C:A:B:A: | D129: =+H111 -> Unid. 3 | E129: =+E1 -> Lima 461 C:A:B:A: | H129: =+D129 -> Unid. 3
D130: =+H130 -> 1A | H130: =+H112 -> 1A
B132: =+F1 -> P/Depósito/transferencia en Bco Santander Rio
B133: =+F2 -> Cta. Cte. $ N° 210-1950/3
B134: =+F3 -> CBU 0720210220000000195036 | E134: G A | F134: =+F115 -> 889417.74 | H134: =+D1 -> 46037
B135: =+F4 -> CUIT: 30-53267348-4 | E135: G B | F135: =+F116 -> 15550
E136: D A | F136: =+F119 -> -29700
E137: INT | F137: =+'RES CUENTA'!R17 -> 0
E138: OTROS | F138: =+F117+F118 -> 0
B139: =+$G$30 -> 46037 | C139: =+F121 -> 875267.74 | E139: TOT | F139: =+F121 -> 875267.74
E149: =+$B$1 -> 46143 | G149: =+$D$1 -> 46037
B152: =+B5 -> Franco Lippi | E152: =+E1 -> Lima 461 C:A:B:A: | H152: Unid. 4
H153: =+'RES CUENTA'!A18 -> 1B
B156: Expensas Gastos A | D156: =+'RES CUENTA'!L25 -> 10859801 | E156: =+'RES CUENTA'!G18 -> 8.19 | F156: =+D156*E156/100 -> 889417.74
B157: Expensas Gastos B | D157: =+'RES CUENTA'!M25 -> 125000 | E157: =+'RES CUENTA'!H18 -> 12.44 | F157: =+D157*E157/100 -> 15550
B158: Cable | D158: =+'RES CUENTA'!N18 -> 0 | E158: 0 | F158: =+D158 -> 0
B159: Cuota extra | D159: 0 | E159: 0 | F159: 0
B160: Deuda Anterior | D160: =+'RES CUENTA'!Q18 -> 0 | E160: 0 | F160: =+D160 -> 0
B161: Intereses | D161: =+'RES CUENTA'!R18 -> 0 | E161: 0 | F161: =+D161 -> 0
F162: =SUM(F156:F161) -> 904967.74
B167: =+B152 -> Franco Lippi | E167: =+B152 -> Franco Lippi
H168: Unid. 4
B169: =+E1 -> Lima 461 C:A:B:A: | D169: Unid. 4 | E169: =+E1 -> Lima 461 C:A:B:A: | H169: =+H153 -> 1B
...

Sheet Hoja 3

Sheet Hoja2
A1: Local
A2: enero | B2: 2002 | C2: 593 | D2: 2950
A3: feb | C3: 720 | D3: 3589
A4: abrul | B4: 2002 | C4: 622 | D4: 3100
A6: mayo | C6: 697 | D6: 3472
A7: julio | B7: 2002 | C7: 677 | D7: 3379
A8: agost | C8: 689 | D8: 3430
A9: set | C9: 687 | D9: 3427
A10: dic | B10: 2002 | C10: 667 | D10: 3327
A11: enero | B11: 2003 | C11: 646 | D11: 3219
A12: feb | C12: 881 | D12: 4391
A13: marz | C13: 689 | D13: 3436
A14: abruil | C14: 680
A15: mayo | C15: 780

Sheet Hoja1
A2: CONSORCIO SANTIAGO DEL ESTERO 338
A4: DETERMINACIÓN DE LAS COBRANZAS Y DE LOS SALDOS PENDIENTES DE COBRO AL 06/06/03
A7: Deuda anterior incluye intereses | E7: 60393.6
A8: Cobrado | E8: =-8052.31 -> -8052.31
A9: Deuda anterior (solamente capital) | E9: -50960.07
A10: Intereses pedientes de cobro correspondiente a deuda anterior | E10: =-'RES CUENTA'!#REF!+0.9 -> #REF!
A11: Importe incluido en Cobranzas y no en resumen de cuenta por no haber sido identificado | E11: 100
A12: Control | E12: =SUM(E7:E11) -> #REF!
