Workbook

Sheet LIQ
A1: MIS EXPENSAS- Liquidación de | H1: 46143
A2: ADMINISTRACION: | G2: CONSORCIO DE PROPIETARIOS:
A3: MARIANO CAUVIN | G3: URUGUAY 1025/27/29 CAP. FED.
A4: AV.BELGRANO 1270 5°A C.A.B.A. | G4: CUIT: 30-58026090-6
A5: masoca_administraciones@hotmail.com | E5: 4381-0014 | G5: CLAVE SUTERH: 1542
A6: 20-16975070-0 | E6: Responsable Monotributo
A7: R.P.A. N° 470 | E7: URGENCIAS 155248-3729
B9: PAGOS DEL PERIODO | F9: GASTOS "A" | G9: GASTOS "B" | H9: TOTAL | I9: % | K9: EFVO | L9: BANCO | M9: PEND | N9: TOTAL
B10: REMUNERACIONES AL PERSONAL Y CARGAS SOCIALES | H10: =SUM(F13:F38)+G14+G33+G34+G35+G36+G37+G38 -> 4278582.9 | I10: =+H10/$H$74 -> 0.67125177 | K10: 0 | L10: =+F33+F34+F35+F36+F37+F38+G33+G34+G35+G36+G37+G38 -> 1881373.9 | M10: =+F14+G14+F23 -> 2397209 | N10: =SUM(K10:M10) -> 4278582.9
B11: Conf. Art. 10 inc.d Ley N°941
A12: 1 | B12: DETALLE DE SUELDOS Y CARGAS SOCIALES:
B13: Vigilador diurno:
B14: Rodriguez Alfredo Raúl (20-33199231-4): sueldo neto 05/26 | F14: =1193914*0.635 -> 758135.39 | G14: =1193914*0.365 -> 435778.61
B15: Sueldo Básico | D15: 1056829
B16: Plus por Antigüedad -15 años | D16: 315174
B17: Adicional viáticos | D17: 73765.1
B18: Adicional remuneratorio | D18: 80000
B19: Total bruto | D19: =SUM(D15:D18) -> 1525768.1
B20: Dtos legales | D20: -331854.56
B21: Sueldo neto | D21: =SUM(D19:D20) -> 1193913.5
B22: Encargado permanente con vivienda:
B23: Coronel Edgardo Dario (20-27589007-4): sueldo neto 05/26 | F23: 1203295 | G23: 0
B24: Sueldo Básico | D24: 1089785
B25: Plus por Antigüedad- 15 años | D25: 315174
B26: Retiro de residuos | D26: 21349.9
B27: Valor vivienda | D27: 7130.4
B28: Clasif. residuos Resol 243/13 SSRT | D28: 33429.7
B29: Adicional remuneratorio | D29: 80000
B30: Total bruto | D30: =SUM(D24:D29) -> 1546869
B31: Dtos legales | D31: -343574.41
B32: Sueldo neto | D32: =SUM(D30:D31) -> 1203294.6
B33: ARCA AFIP F.931:Cargas sociales: SIJP y Obra Social 04/26 | F33: =1224261.79*0.635 -> 777406.24 | G33: =1224261.79*0.365 -> 446855.55
B34: ARCA AFIP F 931: ART 04/26 | F34: =225192.26*0.635 -> 142997.09 | G34: =225192.26*0.365 -> 82195.175
B35: ARCA AFIP F.931: SCVO 04/26 | F35: =849.24*0.635 -> 539.2674 | G35: =849.24*0.365 -> 309.9726 | J35: junio
B36: SUTERH 04/26 | F36: =134844.48*0.635 -> 85626.245 | G36: =134844.48*0.365 -> 49218.235
B37: FATERYH 04/26 | F37: =281243.37*0.635 -> 178589.54 | G37: =281243.37*0.365 -> 102653.83
B38: FATERYH - SERACARH 04/26 | F38: =14982.72*0.635 -> 9514.0272 | G38: =14982.72*0.365 -> 5468.6928
B40: PAGOS POR SUMINISTROS, SERVICIOS, ABONOS Y SEGUROS
B41: Conf. Art. 10 inc. e y f Ley N°941
B42: SERVICIOS PUBLICOS Y TASAS | H42: =SUM(F43:F45)+G44 -> 604851.11 | I42: =+H42/H74 -> 0.094892956 | K42: 0 | L42: =+F45+F44+G44+F43 -> 604851.11 | N42: =+K42+L42+M42 -> 604851.11
B43: Edesur Portería 05/26. Medidor 3832445 Cliente 284784. Débito 26/05 | F43: 17563.56 | G43: 0
B44: Edesur Edificio 05/26. Medidor 73590 Cliente 80060529. Débito 22/05 | F44: =467786.04*0.8 -> 374228.83 | G44: =467786.04*0.2 -> 93557.208
B45: Metrogas Medidor 3104606 Cliente 012866213. tramo 2/2-27/02 al 27/03 | F45: 119501.51 | G45: 0
A47: 3 | B47: ABONOS DE SERVICIOS | H47: =SUM(F48:F52) -> 395606.22 | I47: =+H47/H74 -> 0.062065264 | K47: 0 | L47: =+F48+F49+F50+F52 -> 395606.22 | M47: 0 | N47: =+K47+L47+M47 -> 395606.22
B48: 6M Ascensores (30-71575069-0): mant de ascensores 04/26 FC 9407 | F48: 180000 | G48: 0
B49: ARCH (27-04933062-1): certificación profesional de calderas 04/26 FC 5086 | F49: 56000 | G49: 0
B50: MAFRAP Desinfecciones Urbanas SRL(30-64714402-7): servicio desinf. 04/26 FC 180558 | F50: 85270 | G50: 0
B51: FUEGOTECNIC SRL (30-70839022-0): cuota 7/12 mant. anual y controles periodicos | G51: 0
B52: de la red fija contra incendio FC 161825 | F52: 74336.22 | G52: 0
A54: 4 | B54: MANTENIMIENTO DE PARTES COMUNES | H54: 0 | I54: =+H54/H74 -> 0 | K54: 0 | L54: 0 | M54: 0 | N54: =+K54+L54+M54 -> 0
A56: 5 | B56: TRABAJOS DE REPARACIONES EN UNIDADES | H56: 0 | I56: =+H56/H74 -> 0 | K56: 0 | L56: 0 | M56: 0
A58: 6 | B58: GASTOS BANCARIOS | H58: =SUM(F59:F59) -> 125663.97 | I58: =+H58/H74 -> 0.019714977 | K58: 0 | L58: =+F59 -> 125663.97 | N58: =+K58+L58+M58 -> 125663.97
B59: ICBC: gastos bancarios e impuestos 05/26 | F59: 125663.97 | G59: 0
A61: 7 | B61: GASTOS DE LIMPIEZA | H61: =+F62 -> 88000 | I61: =+H61/H74 -> 0.013806009 | K61: 0 | L61: =+H61 -> 88000 | M61: 0 | N61: =+K61+L61+M61 -> 88000
B62: PIPACH (30-55129402-8): arts de limpieza TK 80912 | F62: 88000 | G62: 0
A64: 8 | B64: GASTOS DE ADMINISTRACIÓN Y LEGALES | H64: =SUM(F65:F65) -> 641000 | I64: =+H64/$H$74 -> 0.10056423 | J64: 46143 | K64: 0 | L64: 0 | M64: =+F65 -> 641000 | N64: =+K64+L64+M64 -> 641000
B65: Honorarios Administración 05/26 | F65: 641000 | G65: 0
A67: 9 | B67: SEGUROS | H67: =SUM(F69:F71) -> 240331.74 | I67: =+H67/$H$74 -> 0.037704799 | K67: 0 | L67: =+H67 -> 240331.74 | M67: 0 | N67: =+K67+L67+M67 -> 240331.74
B68: Allianz (30-50003721-7): seguro integral de consorcio. Póliza 250230768999
B69: vigencia 22/09/25 al 22/09/26. Cuota 7/10 y endoso cuota 2/5 | F69: 222789.87 | G69: 0
B70: Berkley: seguro de vida colectivo. Póliza 37532 vigencia
B71: vigencia 01/10/2025 al 01/10/26. Cuota 8/10 | F71: 17541.87 | G71: 0
A73: 10 | B73: OTROS | H73: 0 | I73: =+H73/H74 -> 0 | K73: 0 | L73: 0 | M73: 0 | N73: =+K73+L73+M73 -> 0
B74: Total de pagos | F74: =SUM(F12:F73) -> 5157998.6 | G74: =SUM(G12:G73) -> 1216037.3 | H74: =SUM(H10:H73) -> 6374035.9 | I74: =+H74/H74 -> 1 | K74: =SUM(K10:K73) -> 0 | L74: =SUM(L10:L73) -> 3335826.9 | M74: =SUM(M10:M73) -> 3038209 | N74: =SUM(N10:N73) -> 6374035.9 | O74: =+H74-N74 -> 0
B76: ESTADO FINANCIERO | H76: $ | K76: BANCO | M76: ICBC | N76: EFVO | O76: PENDIENTE | P76: TOTAL | Q76: TOTAL CONT
B77: Conf. Art. 10 inc. c Ley N°941
B78: Saldo anterior | H78: =+[1]LIQ!$H$83 -> 14331636 | K78: S INICIAL | M78: 17257068 | N78: 34500 | O78: -2959868.8 | P78: =SUM(M78:O78) -> 14331699 | Q78: =+H78 -> 14331636 | R78: =+P78-Q78 -> 63.375335
B79: Cobranzas del período | H79: =+'RES CUENTA'!X26+'RES CUENTA'!Y26 -> 8866587 | K79: COB DEL MES | M79: =+'RES CUENTA'!X26 -> 8866587 | N79: =+'RES CUENTA'!Y26 -> 0 | O79: 0 | P79: =SUM(M79:O79) -> 8866587 | Q79: =+H79 -> 8866587 | R79: =+P79-Q79 -> 0
B80: Cobranza bancaria del período sin identificar no aplicada a la unidad | H80: =+M80 -> 0 | K80: COB SIN IDEN | M80: 0 | O80: 0 | P80: =SUM(M80:O80) -> 0 | Q80: =+H80 -> 0 | R80: =+P80-Q80 -> 0
B81: Cobranza bancaria identificada de meses anteriores | H81: =+M81 -> 0 | K81: CO IDEN | M81: =+'RES CUENTA'!X27 -> 0 | N81: 0 | O81: 0 | P81: =SUM(M81:O81) -> 0 | Q81: =+H81 -> 0 | R81: =+P81-Q81 -> 0
B82: Pagos del período Gastos "A" | H82: =-F74 -> -5157998.6 | K82: GASTOS DEL MES | M82: =-F59-F33-G33-G34-F34-F35-G35-F69-F45-F36-G36-F37-G37-F38-G38-F48-F49-F50-F62-F71-F43-F52-F44-G44 -> -3335826.9 | N82: =-K74 -> 0 | O82: =-M74 -> -3038209 | P82: =SUM(M82:O82) -> -6374035.9 | Q82: =+H82+H83 -> -6374035.9 | R82: =+P82-Q82 -> 0
B83: Pagos del período Gastos "B" | H83: =-G74 -> -1216037.3 | K83: GASTOS MES ANT | M83: =-1165767-1172196-550000-71905.8 -> -2959868.8 | N83: 0 | O83: =-M83-N83 -> 2959868.8 | P83: 0 | R83: 0
B84: Saldo al cierre | H84: =SUM(H78:H83) -> 16824187 | K84: ANTICIPO SUELDO | M84: 0 | N84: 0 | O84: 0 | P84: =SUM(M84:O84) -> 0
K85: DEPOSITO/ RETIRO | M85: 0 | N85: 0 | O85: 0 | P85: 0 | R85: 0
K86: SALDO | M86: =SUM(M78:M85) -> 19827959 | N86: =SUM(N78:N85) -> 34500 | O86: =SUM(O78:O85) -> -3038209 | P86: =SUM(P78:P85) -> 16824250 | Q86: =SUM(Q78:Q85) -> 16824187 | R86: =+P86-Q86 -> 63.375335
K87: SALDO S/EXTRACTO | M87: 19827959 | N87: =+M92+M94+M93 -> 34500 | O87: =+M90 -> -3038209 | P87: =SUM(M87:O87) -> 16824250 | Q87: =+P87 -> 16824250
K88: DIF | M88: =+M86-M87 -> 0 | N88: =+N86-N87 -> 0 | O88: =+O86-O87 -> 0 | P88: =+P86-P87 -> 0 | Q88: =+Q87-Q86 -> 63.375335
K90: a debitar | M90: =-1203295-1193914-641000 -> -3038209 | N90: =+M90-M83 -> -78340.2 | O90: FUEGOTECNIC 06/23? | P90: $ 8331,75 CH 84 RECHAZADO 07/23
K91: banco | M91: =+M87+M90 -> 16789750 | O91: SE REVIERTE EN LIQ 11/2025
K92: efvo | M92: 34500
K93: debe | M93: 0 | Y93: =19609-105 -> 19504
K94: YA PAGADO ANTI SUELDO | M94: 0
B95: AFIP F.931:Cargas sociales: SIJP y Obra Social 05/26 | F95: =443996.06+576407.08+78352.25+156704.49 -> 1255459.9 | K95: total | M95: =SUM(M91:M94) -> 16824250 | N95: =+H84 -> 16824187
B96: AFIP F 931: ART 05/26 | F96: 230905.15 | M96: =+H84 -> 16824187
B97: AFIP F.931: SCVO 05/26 | F97: 861.24 | M97: =+M96-M95 -> -63.375335
B98: SUTERH 05/26 | F98: =+SUELDO!I61 -> 138268.67
B99: FATERYH 05/26 | F99: =+SUELDO!M61+44962*2 -> 289645.41
B100: FATERYH - SERACARH 05/26 | F100: =+SUELDO!T61 -> 15363.185 | N100: =+N99+M97 -> -63.375335
B101: SERACARH- Capacitación
B102: 2 aguinaldo y bonif anual dario
B103: 2 aguinaldo y bonif anual alfredo
F104: =SUM(F95:F103) -> 1930503.5
F109: =+H84 -> 16824187
F110: =+'RES CUENTA'!Q26 -> 8612689.7
F111: =-H74 -> -6374035.9
F112: =+F109+F110+F111 -> 19062841

Sheet RES CUENTA
A2: =+LIQ!A2 -> ADMINISTRACION: | N2: =+LIQ!G2 -> CONSORCIO DE PROPIETARIOS:
A3: =+LIQ!A3 -> MARIANO CAUVIN | N3: =+LIQ!G3 -> URUGUAY 1025/27/29 CAP. FED.
A4: =+LIQ!A4 -> AV.BELGRANO 1270 5°A C.A.B.A. | N4: =+LIQ!G4 -> CUIT: 30-58026090-6
A5: =+LIQ!A5 -> masoca_administraciones@hotmail.com | G5: =+LIQ!E5 -> 4381-0014 | N5: =+LIQ!G5 -> CLAVE SUTERH: 1542
A6: =+LIQ!A6 -> 20-16975070-0 | G6: =+LIQ!E6 -> Responsable Monotributo
A7: =+LIQ!A7 -> R.P.A. N° 470 | G7: =+LIQ!E7 -> URGENCIAS 155248-3729
A9: ESTADO DE CUENTAS Y PRORRATEO DE GASTOS AL 31/05/2026
A10: AVISO DE PAGO : FECHA DE VENCIMIENTO 10/06/2026
X11: Cobranza
A12: DTO | B12: U.F. | C12: DTO | D12: NOMBRE | E12: SALDO ANTERIOR | F12: SU PAGO | G12: % A | H12: EXP. A | I12: %B | J12: EXP. B | K12: %C | L12: S/ASAMBLEA | M12: OTROS | N12: TOTALES DEL MES | O12: DEUDA | P12: INTERE-SES | Q12: TOTAL | R12: FONDO | S12: OBSERVACIONES | T12: OBSERVACIONES | U12: U.F. | V12: Dif | W12: S/ liquid | X12: BANCO | Y12: EFECTIVO | AG12: METROS | AH12: METROS COMPL | AJ12: DUEÑO | AK12: INQUILINO
A13: LOC 1 | B13: 1 | C13: 1-A | D13: DALLAVIA ALEJANDRO A. | E13: =+W13 -> 168188 | F13: =-X13-Y13 -> -168188 | G13: 2.5 | H13: =+$H$26*G13/100 -> 168797 | I13: 0 | J13: =+$J$26*I13/100 -> 0 | L13: =+G13*$L$26/100 -> 0 | M13: 0 | N13: =+H13+J13+L13 -> 168797 | O13: 0 | P13: 0 | Q13: =SUM(N13:P13) -> 168797 | R13: 0 | U13: 1 | V13: =+W13-X13-Y13 -> 0 | W13: 168188 | X13: 168188 | Z13: =1125+1827 -> 2952 | AC13: =+P13-AB13 -> 0 | AD13: davinquilmes | AG13: 41.52 | AK13: davinquilmes@yahoo.com.ar
A14: LOC 2 | B14: =+B13+1 -> 2 | C14: 1-B | D14: MBAZBAZ MARIELA L. Y OTRO | E14: =+W14 -> 361259.34 | F14: =-X14-Y14 -> 0 | G14: 2.61 | H14: =+$H$26*G14/100 -> 176224.07 | I14: 0 | J14: =+$J$26*I14/100 -> 0 | L14: =+G14*$L$26/100 -> 0 | M14: 0 | N14: =+H14+J14+L14 -> 176224.07 | O14: =+INTERESES!R9+INTERESES!S10 -> 352448.14 | P14: =+INTERESES!V11 -> 26433.61 | Q14: =SUM(N14:P14) -> 555105.81 | R14: 0 | U14: =+U13+1 -> 2 | V14: =+W14-X14-Y14 -> 361259.34 | W14: 361259.34 | Z14: 1174 | AC14: =+P14-AB14 -> 26433.61 | AG14: 43.42 | AJ14: marielambazbaz@yahoo.com.ar | AK14: aletasiounis@gmail.com
A15: ´1-03 | B15: =+B14+1 -> 3 | C15: 2-A | D15: RIMASA S.A. | E15: =+W15 -> 720807.75 | F15: =-X15-Y15 -> -720808 | G15: =8.58+0.09 -> 8.67 | H15: =+$H$26*G15/100 -> 585388 | I15: =+G15/94.89*100 -> 9.1368954 | J15: =+$J$26*I15/100 -> 135419.75 | L15: =+G15*$L$26/100 -> 0 | M15: 0 | N15: =+H15+J15+L15 -> 720807.75 | O15: 0 | P15: 0 | Q15: =SUM(N15:P15) -> 720807.75 | R15: 0 | U15: =+U14+1 -> 3 | V15: =+W15-X15-Y15 -> -0.25060133 | W15: 720807.75 | X15: 720808 | Z15: 3902 | AC15: =+P15-AB15 -> 0 | AD15: lalor | AG15: 142.73 | AH15: 1.52 | AJ15: elalor@fibertel.com.ar/eduardolalor@hotmail.com
A16: ´2-04 | B16: =+B15+1 -> 4 | C16: 2-B | D16: CANOPUS TRAVEL | E16: =+W16 -> 720807.75 | F16: =-X16-Y16 -> -720808 | G16: =8.58+0.09 -> 8.67 | H16: =+$H$26*G16/100 -> 585388 | I16: =+G16/94.89*100 -> 9.1368954 | J16: =+$J$26*I16/100 -> 135419.75 | L16: =+G16*$L$26/100 -> 0 | M16: 0 | N16: =+H16+J16+L16 -> 720807.75 | O16: 0 | P16: 0 | Q16: =SUM(N16:P16) -> 720807.75 | R16: 0 | U16: =+U15+1 -> 4 | V16: =+W16-X16-Y16 -> -0.25060133 | W16: 720807.75 | X16: 720808 | Z16: 3902 | AC16: =+P16-AB16 -> 0 | AG16: 142.73 | AH16: 1.52 | AJ16: dalinda@canopustravel.com | AN16: 30-55608839-6
A17: ´3-05 | B17: =+B16+1 -> 5 | C17: 3-A | D17: LASTIRI JORGE ANTONIO | E17: =+W17 -> 720807.75 | F17: =-X17-Y17 -> -720808 | G17: =8.58+0.09 -> 8.67 | H17: =+$H$26*G17/100 -> 585388 | I17: =+G17/94.89*100 -> 9.1368954 | J17: =+$J$26*I17/100 -> 135419.75 | L17: =+G17*$L$26/100 -> 0 | M17: 0 | N17: =+H17+J17+L17 -> 720807.75 | O17: 0 | P17: 0 | Q17: =SUM(N17:P17) -> 720807.75 | R17: 0 | U17: =+U16+1 -> 5 | V17: =+W17-X17-Y17 -> -0.25060133 | W17: 720807.75 | X17: 720808 | Z17: 3902 | AC17: =+P17-AB17 -> 0 | AG17: 142.73 | AH17: 1.52 | AJ17: oficinauruguay3@gmail.com | AK17: mbianchi@vialven.com.ar
A18: ´4-06 | B18: =+B17+1 -> 6 | C18: 3-B | D18: GASTALDI JOSE MARIA | E18: =+W18 -> 720807.75 | F18: =-X18-Y18 -> -721000 | G18: =8.58+0.09 -> 8.67 | H18: =+$H$26*G18/100 -> 585388 | I18: =+G18/94.89*100 -> 9.1368954 | J18: =+$J$26*I18/100 -> 135419.75 | L18: =+G18*$L$26/100 -> 0 | M18: 0 | N18: =+H18+J18+L18 -> 720807.75 | O18: -192 | P18: 0 | Q18: =SUM(N18:P18) -> 720615.75 | R18: 0 | U18: =+U17+1 -> 6 | V18: =+W18-X18-Y18 -> -192.2506 | W18: 720807.75 | X18: 721000 | Z18: 3902 | AC18: =+P18-AB18 -> 0 | AD18: scardaccione/BARTOLO | AG18: 142.73 | AH18: 1.52 | AJ18: daniela_gastaldi@hotmail.com/jmarianogastaldi@estudiogastaldi.com.ar | AK18: mscardac@gmail.com
A19: ´5-07 | B19: =+B18+1 -> 7 | C19: 4-A | D19: ROCHERAY & TESSI | E19: =+W19 -> 720807.75 | F19: =-X19-Y19 -> -720808 | G19: =8.58+0.09 -> 8.67 | H19: =+$H$26*G19/100 -> 585388 | I19: =+G19/94.89*100 -> 9.1368954 | J19: =+$J$26*I19/100 -> 135419.75 | L19: =+G19*$L$26/100 -> 0 | M19: 0 | N19: =+H19+J19+L19 -> 720807.75 | O19: 0 | P19: 0 | Q19: =SUM(N19:P19) -> 720807.75 | R19: 0 | U19: =+U18+1 -> 7 | V19: =+W19-X19-Y19 -> -0.25060133 | W19: 720807.75 | X19: 720808 | Z19: 3902 | AC19: =+P19-AB19 -> 0 | AD19: 3vtech | AG19: 142.73 | AH19: 1.52 | AJ19: pilar_rocheray@hotmail.com
A20: ´6-08 | B20: =+B19+1 -> 8 | C20: 4-B | D20: LISOPRAWSKI SILVIO | E20: =+W20 -> 720807.75 | F20: =-X20-Y20 -> -720808 | G20: =8.58+0.09 -> 8.67 | H20: =+$H$26*G20/100 -> 585388 | I20: =+G20/94.89*100 -> 9.1368954 | J20: =+$J$26*I20/100 -> 135419.75 | L20: =+G20*$L$26/100 -> 0 | M20: 0 | N20: =+H20+J20+L20 -> 720807.75 | O20: 0 | P20: 0 | Q20: =SUM(N20:P20) -> 720807.75 | R20: 0 | U20: =+U19+1 -> 8 | V20: =+W20-X20-Y20 -> -0.25060133 | W20: 720807.75 | X20: 720808 | Z20: 3902 | AC20: =+P20-AB20 -> 0 | AG20: 142.73 | AH20: 1.52 | AJ20: adenicola@estudiolisoprawski.com.ar | AN20: 20-10399484-6
A21: ´7-09 | B21: =+B20+1 -> 9 | C21: 5-A | D21: SUELOMAR S.A. | E21: =+W21 -> 720807.75 | F21: =-X21-Y21 -> -720808 | G21: =8.58+0.09 -> 8.67 | H21: =+$H$26*G21/100 -> 585388 | I21: =+G21/94.89*100 -> 9.1368954 | J21: =+$J$26*I21/100 -> 135419.75 | L21: =+G21*$L$26/100 -> 0 | M21: 0 | N21: =+H21+J21+L21 -> 720807.75 | O21: 0 | P21: 0 | Q21: =SUM(N21:P21) -> 720807.75 | R21: 0 | U21: =+U20+1 -> 9 | V21: =+W21-X21-Y21 -> -0.25060133 | W21: 720807.75 | X21: 720808 | Z21: =3902+7308 -> 11210 | AC21: =+P21-AB21 -> 0 | AG21: 142.73 | AH21: 1.52 | AJ21: contadormarino@fibertel.com.ar
A22: ´8-10 | B22: =+B21+1 -> 10 | C22: 5-B | D22: FEBOMAR SAICF | E22: =+W22 -> 720807.75 | F22: =-X22-Y22 -> -720808 | G22: =8.58+0.09 -> 8.67 | H22: =+$H$26*G22/100 -> 585388 | I22: =+G22/94.89*100 -> 9.1368954 | J22: =+$J$26*I22/100 -> 135419.75 | L22: =+G22*$L$26/100 -> 0 | M22: 0 | N22: =+H22+J22+L22 -> 720807.75 | O22: 0 | P22: 0 | Q22: =SUM(N22:P22) -> 720807.75 | R22: 0 | U22: =+U21+1 -> 10 | V22: =+W22-X22-Y22 -> -0.25060133 | W22: 720807.75 | X22: 720808 | Z22: =3902+37426 -> 41328 | AC22: =+P22-AB22 -> 0 | AD22: cobrados | AG22: 142.73 | AH22: 1.52 | AJ22: contadormarino@fibertel.com.ar
A23: ´9-11 | B23: =+B22+1 -> 11 | C23: 6-A | D23: DICARLO DORA C. | E23: =+W23 -> 720807.75 | F23: =-X23-Y23 -> -720808 | G23: =8.58+0.09 -> 8.67 | H23: =+$H$26*G23/100 -> 585388 | I23: =+G23/94.89*100 -> 9.1368954 | J23: =+$J$26*I23/100 -> 135419.75 | L23: =+G23*$L$26/100 -> 0 | M23: 0 | N23: =+H23+J23+L23 -> 720807.75 | O23: 0 | P23: 0 | Q23: =SUM(N23:P23) -> 720807.75 | R23: 0 | U23: =+U22+1 -> 11 | V23: =+W23-X23-Y23 -> -0.25060133 | W23: 720807.75 | X23: 720808 | Z23: 3902 | AC23: =+P23-AB23 -> 0 | AG23: 142.73 | AH23: 1.52 | AJ23: dcdicarlo@gmail.com
A24: ´10-12 | B24: =+B23+1 -> 12 | C24: 6-B | D24: DICARLO DORA C. | E24: =+W24 -> 631018.55 | F24: =-X24-Y24 -> -631019 | G24: =7.5+0.09 -> 7.59 | H24: =+$H$26*G24/100 -> 512467.69 | I24: =+G24/94.89*100 -> 7.9987354 | J24: =+$J$26*I24/100 -> 118550.86 | L24: =+G24*$L$26/100 -> 0 | M24: 0 | N24: =+H24+J24+L24 -> 631018.55 | O24: 0 | P24: 0 | Q24: =SUM(N24:P24) -> 631018.55 | R24: 0 | U24: =+U23+1 -> 12 | V24: =+W24-X24-Y24 -> -0.45121846 | W24: 631018.55 | X24: 631019 | Z24: 3416 | AC24: =+P24-AB24 -> 0 | AG24: 142.56 | AH24: 1.52 | AJ24: dicarlodora@hotmail.com
A25: ´11-13 | B25: =+B24+1 -> 13 | C25: 7-A | D25: ORO 2999 S.A. | E25: =+W25 -> 1579915.8 | F25: =-X25-Y25 -> -1579916 | G25: =9.18+0.09 -> 9.27 | H25: =+$H$26*G25/100 -> 625899.28 | I25: =+G25/94.89*100 -> 9.7692064 | J25: =+$J$26*I25/100 -> 144791.36 | L25: =+G25*$L$26/100 -> 0 | M25: 0 | N25: =+H25+J25+L25 -> 770690.64 | O25: 0 | P25: 0 | Q25: =SUM(N25:P25) -> 770690.64 | R25: 0 | U25: =+U24+1 -> 13 | V25: =+W25-X25-Y25 -> -0.19080765 | W25: 1579915.8 | X25: =1000000+579916 -> 1579916 | Z25: =4172-4 -> 4168 | AC25: =+P25-AB25 -> 0 | AG25: 171.49 | AH25: 1.52 | AJ25: fernando.iuliano@iulianocooreman.com.ar | AK25: makabri2@gmail.com
D26: TOTALES | E26: =SUM(E13:E25) -> 9227651.4 | F26: =SUM(F13:F25) -> -8866587 | G26: =SUM(G13:G25) -> 100 | H26: =(8234000)*0.82 -> 6751880 | I26: =SUM(I13:I25) -> 100 | J26: =(8234000)*0.18 -> 1482120 | K26: =SUM(K13:K25) -> 0 | L26: 0 | M26: =SUM(M13:M25) -> 0 | N26: =SUM(N13:N25) -> 8234000 | O26: =SUM(O13:O25) -> 352256.14 | P26: =SUM(P13:P25) -> 26433.61 | Q26: =SUM(Q13:Q25) -> 8612689.7 | V26: =+W26-X26-Y26 -> 361064.44 | W26: 9227651.4 | X26: =SUM(X13:X25) -> 8866587 | Y26: =SUM(Y13:Y25) -> 0 | Z26: =SUM(Z13:Z25) -> 91562 | AC26: =+P26-AB26 -> 26433.61
V27: =+O26+P26 -> 378689.75 | X27: 0
A28: LAS EXPENSAS VENCEN EL DIA 10. PAGO FUERA DE TERMINO 5% DE INTERÉS MENSUAL
A34: FORMAS DE PAGO:
A35: Depósito o transferencia:
A36: Titular: | D36: CONS DE PROPIETARIOS URUGUAY 1025 27 29
A37: Banco: | D37: ICBC
A38: N°Cuenta: | D38: Cuenta: CC $ 0538/02104658/84
A39: CBU: | D39: 0150538202000104658840
A40: Alias: | D40: BICI.FRASE.BOTE
A43: DATOS DE JUICIOS
A44: Conf. Art. 10 inc. h Ley N°941
A45: CARATULA:
A46: N° EXPEDIENTE:
A47: JUZGADO/SECRETARÍA:
A48: ESTADO
A49: OBJETO:
A50: MONTO RECLAMADO
A53: MANUAL DE BUENAS PRÁCTICAS CONSORCIALES
A54: https://buenosaires.gob.ar/sites/default/files/2025-02/Manual%20buenas%20pr%C3%A1cticas%20consorciales_0.pdf
A57: REGLAMENTO DE COPROPIEDAD
A58: https://drive.google.com/file/d/13IEEGZWXVeYlSGhHHfeB7KnTorha8hGH/view?usp=drive_link
... A69: Disposición Nro: DI-2024-1146-GCABA-DGDYPC
F107: 110739.34
F109: =+SUELDO!I61-0.01 -> 138268.66
F110: =+SUELDO!M61+6932*2+0.01 -> 213585.42
F111: =+SUELDO!T61-0.01 -> 15363.175

Sheet INTERESES
A3: U.F. | B3: DTO | C3: NOMBRE | D3: 39326 | E3: 39356 | F3: 39387 | G3: 39417 | H3: 39448 | I3: 39479 | J3: 39508 | K3: 39539 | L3: 39569 | M3: 39600 | N3: 45962 | O3: 45992 | P3: 46023 | Q3: 46054 | R3: 46082 | S3: 46113 | T3: TASA | U3: DIAS | V3: INTERES
A5: 1 | C5: =+'RES CUENTA'!D13 -> DALLAVIA ALEJANDRO A. | W5: =+'RES CUENTA'!X13+'RES CUENTA'!Y13 -> 168188 | X5: =-'[2]RES CUENTA'!$O$13 -> -123.225 | Y5: =+W5+X5 -> 168064.77
T6: 0.05 | U6: 30 | V6: =+N6*T6/30*U6 -> 0
V7: =SUM(V6:V6) -> 0
A9: 2 | C9: =+'RES CUENTA'!D14 -> MBAZBAZ MARIELA L. Y OTRO | R9: =+'[3]RES CUENTA'!$N$14 -> 176224.07 | T9: 0.05 | U9: 60 | V9: =+R9*T9/30*U9 -> 17622.407 | W9: =+'RES CUENTA'!X14 -> 0 | X9: =-'[4]RES CUENTA'!$P$14 -> -175423.21 | Y9: =+W9+X9 -> -175423.21
S10: =+'[1]RES CUENTA'!$N$14 -> 176224.07 | T10: 0.05 | U10: 30 | V10: =+S10*T10/30*U10 -> 8811.2034
V11: =SUM(V9:V10) -> 26433.61
A13: 3 | C13: =+'RES CUENTA'!D15 -> RIMASA S.A.
T16: 0.05 | U16: 30 | V16: =+Q16*T16/30*U16 -> 0
A18: 4 | C18: =+'RES CUENTA'!D16 -> CANOPUS TRAVEL | T18: 0.05 | U18: 30 | V18: =+#REF!*T18/30*U18 -> #REF!
A20: 5 | C20: =+'RES CUENTA'!D17 -> LASTIRI JORGE ANTONIO | T20: 0.05 | U20: 30 | V20: =+#REF!*T20/30*U20 -> #REF!
A22: 6 | C22: =+'RES CUENTA'!D18 -> GASTALDI JOSE MARIA | T22: 0.05 | U22: 60
T23: 0.05 | U23: 30 | V23: =+N23*T23/30*U23 -> 0
V24: =+V23 -> 0
A25: 7 | C25: =+'RES CUENTA'!D19 -> ROCHERAY & TESSI | T25: 0.05 | U25: 30 | V25: 0
T26: 0.05 | U26: 30 | V26: =+#REF!*T26*U26/30 -> #REF!
V27: =SUM(V25:V26) -> #REF!
A28: 8 | C28: =+'RES CUENTA'!D20 -> LISOPRAWSKI SILVIO | T28: 0.05 | U28: 30 | V28: =+#REF!*T28/30*U28 -> #REF!
A30: 9 | C30: =+'RES CUENTA'!D21 -> SUELOMAR S.A. | X30: -424 | Y30: =+W30+X30 -> -424
Y31: -8482
T32: 0.05 | U32: 60
T33: 0.05 | U33: 30 | V33: =+#REF!*T33/30*U33 -> #REF!
V34: =SUM(V32:V33) -> #REF!
A36: 10 | C36: =+'RES CUENTA'!D22 -> FEBOMAR SAICF | T36: 0.05 | W36: =+'RES CUENTA'!Y22 -> 0 | X36: =-'[5]RES CUENTA'!$O$22 -> -1550.8741 | Y36: =+W36+X36 -> -1550.8741
T37: 0.05 | U37: 60
T38: 0.05 | U38: 30 | V38: =+#REF!*T38/30*U38 -> #REF!
V39: =SUM(V37:V38) -> #REF!
A43: 11 | C43: =+'RES CUENTA'!D23 -> DICARLO DORA C. | W43: =+'RES CUENTA'!X23+'RES CUENTA'!Y23 -> 720808 | X43: =-'[6]RES CUENTA'!$P$23 -> -189980.2 | Y43: =+W43+X43 -> 530827.8
T44: 0.05 | U44: 60 | V44: =+#REF!*T44/30*U44 -> #REF! | Y44: =-633267-633267 -> -1266534
T45: 0.05 | U45: 90 | V45: =+#REF!*T45/30*U45 -> #REF! | Y45: =+Y43+Y44 -> -735706.2
T46: 0.05 | U46: 60 | V46: =+#REF!*T46/30*U46 -> #REF!
T47: 0.05 | U47: 30 | V47: =+#REF!*T47/30*U47 -> #REF!
T48: 0.05 | U48: 30 | V48: =+P48*T48/30*U48 -> 0
V49: =SUM(V44:V48) -> #REF!
A51: 12 | C51: =+'RES CUENTA'!D24 -> DICARLO DORA C. | T51: 0.05 | U51: 30 | V51: =+#REF!*T51/30*U51 -> #REF! | W51: =+'RES CUENTA'!X24+'RES CUENTA'!Y24 -> 631019 | X51: =-'[7]RES CUENTA'!$P$24 -> -48024.119 | Y51: =+W51+X51 -> 582994.88
T52: 0.05 | U52: 30 | V52: =+#REF!*T52/30*U52 -> #REF! | Y52: -329464
T53: 0.05 | U53: 30 | V53: =+#REF!*T53/30*U53 -> #REF! | Y53: =+Y51+Y52 -> 253530.88
T54: 0.05 | U54: 30 | V54: =+#REF!*T54/30*U54 -> #REF!
T55: 0.05 | U55: 60 | V55: =+N55*T55/30*U55 -> 0
T56: 0.05 | U56: 60 | V56: =+O56*T56/30*U56 -> 0
T57: 0.05 | U57: 30 | V57: =+P57*T57/30*U57 -> 0
V58: =SUM(V51:V57) -> #REF!
A60: 13 | C60: =+'RES CUENTA'!D25 -> ORO 2999 S.A. | T60: 0.05 | U60: 60
R61: =+'[3]RES CUENTA'!$N$25 -> 770690.64 | T61: 0.05 | U61: 30 | V61: =+R61*T61/30*U61 -> 38534.532
V62: =SUM(V60:V61) -> 38534.532

Sheet SUELDO
A2: EMPLEADOR: CONS. DE PROP. BERUTI 4575/77 | F2: CUIT: 30-70807291-1
A3: Domicilio: Beruti 4575/77 | F3: Recibo: 1 ORIGINAL
B4: 1425 - Capital Federal | F4: Cuil: 23-11424220-9
A5: PERIODO | B5: APELLIDO Y NOMBRES | F5: Categoria | G5: Legajo
A6: 37653 | B6: OSUNA CLAUDIO R. | F6: 0-03 | G6: 1
A7: BANCO | B7: PERIODO DEPOSITADO | E7: FECHA | F7: TAREA | G7: INGRESO
A8: Nación | B8: Febrero 2003 | E8: 37687 | F8: Enc.Perm c/viv | G8: 37518
A9: CONCEPTOS | E9: UNIDADES | F9: REMUNERAC. | G9: DESCUENT.
A11: BASICO | F11: =374.4 -> 374.4 | I11: feriados,dom
A12: RETIRO DE RESIDUOS | E12: 15 | F12: =+E12*1.26 -> 18.9 | I12: 6
A13: PLUS JARDIN | F13: =16.98 -> 16.98 | I13: 5 | J13: DIAS
A14: PLUS COCHERA | F14: =16.98 -> 16.98 | I14: =+I12*I13 -> 30
A15: DEC.2641/02 | F15: 150 | I15: GRATIFICACION | O15: =+H17+109.74 -> 1832.43
A16: RET. JUBILACION | C16: 7 | D16: % | F16: - | G16: =+$H$17*C16/100 -> 120.5883 | I16: DS NORMALES | K16: 1 | L16: =427.26/30*1 -> 14.242
A17: LEY N 19032 | C17: 3 | D17: % | F17: - | G17: =+$H$17*C17/100 -> 51.6807 | H17: =895.36+727.33+100 -> 1722.69 | I17: HS EXTRAS | K17: 24 | L17: =427.26/200*2*24 -> 102.5424
A18: OBRA SOCIAL | C18: 2.7 | D18: % | F18: - | G18: =+$H$17*C18/100 -> 46.51263 | L18: =+L16+L17 -> 116.7844
A19: ANSSAL | C19: 0.3 | D19: % | F19: - | G19: =+$H$17*C19/100 -> 5.16807 | H19: =SUM(G16:G19) -> 223.9497
A20: CUOTA SINDICAL | C20: 2 | D20: % | F20: - | G20: =+$H$17*C20/100 -> 34.4538 | H20: =59.38+8.76+25.92+5.2+3.5+31.53 -> 134.29 | I20: SETIEMBRE
A21: CAJA PROT FAMILIA | C21: 1 | D21: % | F21: - | G21: =+$H$17*C21/100 -> 17.2269 | H21: =134.29/583.86 -> 0.23000377 | I21: DS NORMALES | K21: 2.5 | L21: =427.26/30*2.5 -> 35.605
H22: =+H21*H17 -> 396.22519 | I22: HS EXTRAS | K22: 40 | L22: =427.26/200*2*40 -> 170.904
D23: TOTAL BRUTO | F23: =SUM(F11:F22) -> 577.26 | H23: =+H22+H19 -> 620.17489
D24: TOTAL DESCUENTOS | F24: - | G24: =SUM(G16:G22) -> 275.6304
D25: TOTAL NETO | F25: - | G25: =+F23-G24 -> 301.6296
D26: REDONDEO | F26: - | G26: =ROUND(G25,0) -> 302
D27: SON PESOS:
A28: FIRMA DEL EMPLEADO | D28: SEICIENTOS OCHENTA Y OCHO
A29: Recibí de la firma cuyo rubro se indica arriba el importe neto de esta liquidación en pago de mi
A30: remuneración correspondiente al período indicado y duplicado de la misma.
A35: EMPLEADOR: CONS. DE PROP. BERUTI 4575/77 | F35: CUIT: 30-70807291-1
A36: Domicilio: Beruti 4575/77 | F36: Recibo: 2 DUPLICADO
B37: 1425 - Capital Federal | F37: Cuil: 23-11424220-9
A38: PERIODO | B38: APELLIDO Y NOMBRES | F38: Categoria | G38: Legajo
A39: =+A6 -> 37653 | B39: OSUNA CLAUDIO R. | F39: 0-03 | G39: 1
A40: BANCO | B40: PERIODO DEPOSITADO | E40: FECHA | F40: TAREA | G40: INGRESO
A41: Nación | B41: Febrero 2003 | E41: =+E8 -> 37687 | F41: Enc.Perm c/viv | G41: 37518
A42: CONCEPTOS | E42: UNIDADES | F42: REMUNERAC. | G42: DESCUENT.
A44: BASICO | F44: =374.4 -> 374.4
A45: HORAS EXTRAS 100% | E45: =3+3+8+3+8+3+8+3+8 -> 47 | F45: =+#REF! -> #REF!
A46: =+#REF! -> #REF! | E46: =+#REF! -> #REF! | F46: =+#REF! -> #REF!
A47: RETIRO DE RESIDUOS | E47: 15 | F47: =+E47*1.26 -> 18.9
A48: PLUS JARDIN | F48: =16.98 -> 16.98
A49: PLUS COCHERA | F49: =16.98 -> 16.98
A50: DEC.2641/02 | F50: =+F15 -> 150
A51: RET. JUBILACION | C51: 7 | D51: % | F51: - | G51: =+$H$17*C51/100 -> 120.5883
A52: LEY Nº 19032 | C52: 3 | D52: % | F52: - | G52: =+$H$17*C52/100 -> 51.6807 | H52: =+G52+G51 -> 172.269 | I52: =+G51+G52 -> 172.269
A53: OBRA SOCIAL | C53: 2.7 | D53: % | F53: - | G53: =+$H$17*C53/100 -> 46.51263 | H53: =+H52+G54 -> 177.43707
A54: ANSSAL | C54: 0.3 | D54: % | F54: - | G54: =+$H$17*C54/100 -> 5.16807 | M54: dario | N54: =+LIQ!D30 -> 1546869
A55: CUOTA SINDICAL | C55: 2 | D55: % | F55: - | G55: =+$H$17*C55/100 -> 34.4538 | M55: alfredo | N55: =+LIQ!D19 -> 1525768.1
A56: CAJA PROT FAMILIA | C56: 1 | D56: % | F56: - | G56: =+$H$17*C56/100 -> 17.2269 | N56: =SUM(N54:N55) -> 3072637.1
L57: =0.75 -> 0.75 | M57: =+N56*L57/100 -> 23044.778
D58: TOTAL BRUTO | F58: =SUM(F44:F57) -> #REF! | I58: Sindicato suterh | L58: =0.75 -> 0.75 | M58: =+K59*L58/100 -> 23044.778
D59: TOTAL DESCUENTOS | F59: - | G59: =SUM(G51:G57) -> 275.6304 | I59: =+K59*J59 -> 46089.556 | J59: =1.5/100 -> 0.015 | K59: =+N56 -> 3072637.1 | L59: 0.04 | M59: =+N59*L59 -> 122905.48 | N59: =+K59 -> 3072637.1 | O59: =+L59+J59 -> 0.055 | P59: 23 | Q59: =+O59*0.02 -> 0.0011 | R59: =+O59*0.01 -> 0.00055 | S59: =+R59+Q59 -> 0.00165 | T59: 0.005
D60: TOTAL NETO | F60: - | G60: =+F58-G59 -> #REF! | I60: =+K59*J60 -> 92179.113 | J60: =3/100 -> 0.03 | L60: 0.01 | M60: =+N59*L60 -> 30726.371 | O60: 707.3 | P60: =23+4.5 -> 27.5 | Q60: =+O60*0.02 -> 14.146 | R60: =+O60*0.01 -> 7.073 | S60: =+R60+Q60 -> 21.219
D61: REDONDEO | F61: - | G61: =ROUND(G60,0) -> #REF! | I61: =+I59+I60 -> 138268.67 | M61: =SUM(M57:M60) -> 199721.41 | O61: 252.8 | Q61: =+Q60+Q59 -> 14.1471 | R61: =+R60+R59 -> 7.07355 | S61: =+Q61+R61 -> 21.22065 | T61: =+K59*T59 -> 15363.185
D62: SON PESOS: | O62: 150.5
A63: FIRMA DEL EMPLEADOR | D63: =+D28 -> SEICIENTOS OCHENTA Y OCHO | I63: art | O63: =+O62+O61+O60 -> 1110.6
A64: Recibí de la firma cuyo rubro se indica arriba el importe neto de esta liquidación en pago de mi | I64: fija | J64: 0.6 | K64: =+J64*2 -> 1.2 | O64: =+O63/K59 -> 0.00036144848
A65: remuneración correspondiente al período indicado y duplicado de la misma. | O65: =0.23+0.045 -> 0.275
I66: porcenta | J66: 3 | K66: =+K59*0.03 -> 92179.113
I67: por empleado | K67: =+K66+K64 -> 92180.313

Sheet RECIBOS
B1: =+LIQ!H1 -> 46143 | D1: 46183 | E1: =+'RES CUENTA'!N3 -> URUGUAY 1025/27/29 CAP. FED. | F1: P/depósito/transferencia en ICBC
B2: =+'RES CUENTA'!D13 -> DALLAVIA ALEJANDRO A. | C2: =+'RES CUENTA'!G13 -> 2.5 | D2: =+'RES CUENTA'!B13 -> 1 | E2: =+'RES CUENTA'!#REF! -> #REF! | F2: Cta. Cte. $ N°538/02104658/84 | H2: 0538/02104658/84
B3: =+'RES CUENTA'!D14 -> MBAZBAZ MARIELA L. Y OTRO | C3: =+'RES CUENTA'!G14 -> 2.61 | D3: =+'RES CUENTA'!B14 -> 2 | E3: =+'RES CUENTA'!#REF! -> #REF! | F3: CBU:0150538202000104658840 | H3: ´01505382020000104658840
B4: =+'RES CUENTA'!D15 -> RIMASA S.A. | C4: =+'RES CUENTA'!G15 -> 8.67 | D4: =+'RES CUENTA'!B15 -> 3 | E4: =+'RES CUENTA'!#REF! -> #REF! | F4: =+LIQ!G4 -> CUIT: 30-58026090-6
B5: =+'RES CUENTA'!D16 -> CANOPUS TRAVEL | C5: =+'RES CUENTA'!G16 -> 8.67 | D5: =+'RES CUENTA'!B16 -> 4 | E5: =+'RES CUENTA'!#REF! -> #REF! | H5: 01505382/0200010465884
B6: =+'RES CUENTA'!D17 -> LASTIRI JORGE ANTONIO | C6: =+'RES CUENTA'!G17 -> 8.67 | D6: =+'RES CUENTA'!B17 -> 5 | E6: =+'RES CUENTA'!#REF! -> #REF!
B7: =+'RES CUENTA'!D18 -> GASTALDI JOSE MARIA | C7: =+'RES CUENTA'!G18 -> 8.67 | D7: =+'RES CUENTA'!B18 -> 6 | E7: =+'RES CUENTA'!#REF! -> #REF!
B8: =+'RES CUENTA'!D19 -> ROCHERAY & TESSI | C8: =+'RES CUENTA'!G19 -> 8.67 | D8: =+'RES CUENTA'!B19 -> 7 | E8: =+'RES CUENTA'!#REF! -> #REF!
B9: =+'RES CUENTA'!D20 -> LISOPRAWSKI SILVIO | C9: =+'RES CUENTA'!G20 -> 8.67 | D9: =+'RES CUENTA'!B20 -> 8 | E9: =+'RES CUENTA'!#REF! -> #REF!
B10: =+'RES CUENTA'!D21 -> SUELOMAR S.A. | C10: =+'RES CUENTA'!G21 -> 8.67 | D10: =+'RES CUENTA'!B21 -> 9 | E10: =+'RES CUENTA'!#REF! -> #REF!
B11: =+'RES CUENTA'!D22 -> FEBOMAR SAICF | C11: =+'RES CUENTA'!G22 -> 8.67 | D11: =+'RES CUENTA'!B22 -> 10 | E11: =+'RES CUENTA'!#REF! -> #REF!
B12: =+'RES CUENTA'!D23 -> DICARLO DORA C. | C12: =+'RES CUENTA'!G23 -> 8.67 | D12: =+'RES CUENTA'!B23 -> 11 | E12: =+'RES CUENTA'!#REF! -> #REF!
B13: =+'RES CUENTA'!D24 -> DICARLO DORA C. | C13: =+'RES CUENTA'!G24 -> 7.59 | D13: =+'RES CUENTA'!B24 -> 12 | E13: =+'RES CUENTA'!#REF! -> #REF!
B14: =+'RES CUENTA'!D25 -> ORO 2999 S.A. | C14: =+'RES CUENTA'!G25 -> 9.27 | D14: =+'RES CUENTA'!B25 -> 13 | E14: =+'RES CUENTA'!#REF! -> #REF!
B15: =+'RES CUENTA'!#REF! -> #REF! | C15: =+'RES CUENTA'!#REF! -> #REF! | D15: =+'RES CUENTA'!#REF! -> #REF! | E15: =+'RES CUENTA'!#REF! -> #REF!
B16: =+'RES CUENTA'!#REF! -> #REF! | C16: =+'RES CUENTA'!#REF! -> #REF! | D16: =+'RES CUENTA'!#REF! -> #REF! | E16: =+'RES CUENTA'!#REF! -> #REF!
B17: =+'RES CUENTA'!#REF! -> #REF! | C17: =+'RES CUENTA'!#REF! -> #REF! | D17: =+'RES CUENTA'!#REF! -> #REF! | E17: =+'RES CUENTA'!#REF! -> #REF!
B18: =+'RES CUENTA'!#REF! -> #REF! | C18: =+'RES CUENTA'!#REF! -> #REF! | D18: =+'RES CUENTA'!#REF! -> #REF! | E18: =+'RES CUENTA'!#REF! -> #REF!
B19: =+'RES CUENTA'!#REF! -> #REF! | C19: =+'RES CUENTA'!#REF! -> #REF! | D19: =+'RES CUENTA'!#REF! -> #REF! | E19: =+'RES CUENTA'!#REF! -> #REF!
B20: =+'RES CUENTA'!#REF! -> #REF! | C20: =+'RES CUENTA'!#REF! -> #REF! | D20: =+'RES CUENTA'!#REF! -> #REF! | E20: =+'RES CUENTA'!#REF! -> #REF!
B21: =+'RES CUENTA'!#REF! -> #REF! | C21: =+'RES CUENTA'!#REF! -> #REF! | D21: =+'RES CUENTA'!#REF! -> #REF! | E21: =+'RES CUENTA'!#REF! -> #REF!
B22: =+'RES CUENTA'!#REF! -> #REF! | C22: =+'RES CUENTA'!#REF! -> #REF! | D22: =+'RES CUENTA'!#REF! -> #REF! | E22: =+'RES CUENTA'!#REF! -> #REF!
B23: =+'RES CUENTA'!D26 -> TOTALES | C23: =+'RES CUENTA'!G26 -> 100 | D23: =+'RES CUENTA'!B26 -> 0 | E23: =+'RES CUENTA'!#REF! -> #REF!
B24: =+'RES CUENTA'!D27 -> 0 | C24: =+'RES CUENTA'!G27 -> 0 | D24: =+'RES CUENTA'!B27 -> 0 | E24: =+'RES CUENTA'!#REF! -> #REF!
B25: =+'RES CUENTA'!D53 -> 0 | C25: =+'RES CUENTA'!G53 -> 0 | D25: =+'RES CUENTA'!B53 -> 0 | E25: =+'RES CUENTA'!#REF! -> #REF!
B26: =+'RES CUENTA'!D56 -> 0 | C26: =+'RES CUENTA'!G56 -> 0 | D26: =+'RES CUENTA'!B56 -> 0 | E26: =+'RES CUENTA'!#REF! -> #REF!
B27: =+'RES CUENTA'!#REF! -> #REF! | C27: =+'RES CUENTA'!#REF! -> #REF! | D27: =+'RES CUENTA'!#REF! -> #REF! | E27: =+'RES CUENTA'!#REF! -> #REF!
B28: =+'RES CUENTA'!#REF! -> #REF! | C28: =+'RES CUENTA'!#REF! -> #REF! | D28: =+'RES CUENTA'!#REF! -> #REF! | E28: =+'RES CUENTA'!#REF! -> #REF!
B29: =+'RES CUENTA'!D26 -> TOTALES | C29: =+'RES CUENTA'!G26 -> 100 | D29: =+'RES CUENTA'!B26 -> 0 | E29: =+'RES CUENTA'!#REF! -> #REF!
C30: =SUM(C2:C24) -> #REF! | E30: =SUM(E2:E24) -> #REF!
E34: =+$B$1 -> 46143 | G34: =+$D$1 -> 46183
H38: Unid. 1
B39: =+B2 -> DALLAVIA ALEJANDRO A. | E39: =+E1 -> URUGUAY 1025/27/29 CAP. FED. | H39: =+'RES CUENTA'!A13 -> LOC 1
B42: Expensas Gastos A | D42: =+'RES CUENTA'!H26 -> 6751880 | E42: =+'RES CUENTA'!G13 -> 2.5 | F42: =+D42*E42/100 -> 168797
B43: Expensas Gastos B | D43: =+'RES CUENTA'!J26 -> 1482120 | E43: =+'RES CUENTA'!I13 -> 0 | F43: =+D43*E43/100 -> 0
B44: s/Asamblea | D44: 0 | E44: 0 | F44: =+'RES CUENTA'!L13 -> 0
B45: Deuda Anterior | D45: =+'RES CUENTA'!O13 -> 0 | E45: 0 | F45: =+D45 -> 0
B46: Intereses | D46: =+'RES CUENTA'!P13 -> 0 | E46: 0 | F46: =+D46+E46 -> 0
B47: Total | F47: =SUM(F42:F46) -> 168797
B53: =+B2 -> DALLAVIA ALEJANDRO A. | E53: =+B2 -> DALLAVIA ALEJANDRO A.
B55: =+E1 -> URUGUAY 1025/27/29 CAP. FED. | D55: =+H38 -> Unid. 1 | E55: =+E1 -> URUGUAY 1025/27/29 CAP. FED. | H55: =+D55 -> Unid. 1
D56: =+H56 -> LOC 1 | H56: =+H39 -> LOC 1
B57: =+F1 -> P/depósito/transferencia en ICBC
B58: =+F2 -> Cta. Cte. $ N°538/02104658/84
B59: =+F3 -> CBU:0150538202000104658840 | E59: G A | F59: =+F42 -> 168797 | H59: =+D1 -> 46183
B60: =+F4 -> CUIT: 30-58026090-6 | E60: G B | F60: =+F43 -> 0
E61: D A | F61: =+F45 -> 0
E62: INT | F62: =+F46 -> 0
E63: s/Asamblea | F63: =+F44 -> 0
B64: =+$G$34 -> 46183 | C64: =+F47 -> 168797 | E64: TOT | F64: =+F47 -> 168797
E75: =+$B$1 -> 46143 | G75: =+$D$1 -> 46183
B78: =+B3 -> MBAZBAZ MARIELA L. Y OTRO | E78: =+E1 -> URUGUAY 1025/27/29 CAP. FED. | H78: Unid. 2
H79: =+'RES CUENTA'!A14 -> LOC 2
B82: Expensas Gastos A | D82: =+'RES CUENTA'!H26 -> 6751880 | E82: =+'RES CUENTA'!G14 -> 2.61 | F82: =+D82*E82/100 -> 176224.07
B83: Expensas Gastos B | D83: =+'RES CUENTA'!J26 -> 1482120 | E83: =+'RES CUENTA'!I14 -> 0 | F83: =+D83*E83/100 -> 0
B84: s/Asamblea | D84: 0 | E84: 0 | F84: =+'RES CUENTA'!L14 -> 0
B85: Deuda Anterior | D85: =+'RES CUENTA'!O14 -> 352448.14 | E85: 0 | F85: =+D85 -> 352448.14
B86: Intereses | D86: =+'RES CUENTA'!P14 -> 26433.61 | E86: 0 | F86: =+'RES CUENTA'!P14 -> 26433.61
B87: Total | F87: =SUM(F82:F86) -> 555105.81
B93: =+B78 -> MBAZBAZ MARIELA L. Y OTRO | E93: =+B78 -> MBAZBAZ MARIELA L. Y OTRO
H94: =+D95 -> Unid. 2
B95: =+E1 -> URUGUAY 1025/27/29 CAP. FED. | D95: Unid. 2 | E95: =+E1 -> URUGUAY 1025/27/29 CAP. FED. | H95: =+H79 -> LOC 2
D96: =+H95 -> LOC 2
B97: =+F1 -> P/depósito/transferencia en ICBC
B98: =+F2 -> Cta. Cte. $ N°538/02104658/84
B99: =+F3 -> CBU:0150538202000104658840 | E99: G A | F99: =+F82 -> 176224.07 | H99: =+D1 -> 46183
B100: =+F4 -> CUIT: 30-58026090-6 | E100: G B | F100: =+F83 -> 0
E101: D A | F101: =+F85 -> 352448.14
E102: INT | F102: =+'RES CUENTA'!P14 -> 26433.61
E103: s/Asamblea | F103: =+F84 -> 0
B104: =+$G$34 -> 46183 | C104: =+F87 -> 555105.81 | E104: TOT | F104: =+F87 -> 555105.81
E110: =+$B$1 -> 46143 | G110: =+$D$1 -> 46183
B114: =+B4 -> RIMASA S.A. | E114: =+E39 -> URUGUAY 1025/27/29 CAP. FED. | H114: Unid. 3
H115: =+'RES CUENTA'!A15 -> ´1-03
B118: Expensas Gastos A | D118: =+'RES CUENTA'!H26 -> 6751880 | E118: =+'RES CUENTA'!G15 -> 8.67 | F118: =+D118*E118/100 -> 585388
B119: Expensas Gastos B | D119: =+'RES CUENTA'!J26 -> 1482120 | E119: =+'RES CUENTA'!I15 -> 9.1368954 | F119: =+D119*E119/100 -> 135419.75
B120: s/Asamblea | D120: 0 | E120: 0 | F120: =+'RES CUENTA'!L15 -> 0
B121: Deuda Anterior | D121: =+'RES CUENTA'!O15 -> 0 | E121: 0 | F121: =+D121 -> 0
B122: Intereses | D122: =+'RES CUENTA'!P15 -> 0 | E122: 0 | F122: =+D122 -> 0
B123: Total | F123: =SUM(F118:F122) -> 720807.75
B129: =+B114 -> RIMASA S.A. | E129: =+B129 -> RIMASA S.A.
B131: =+E1 -> URUGUAY 1025/27/29 CAP. FED. | D131: =+H114 -> Unid. 3 | E131: =+E1 -> URUGUAY 1025/27/29 CAP. FED. | H131: =+D131 -> Unid. 3
D132: =+H132 -> ´1-03 | H132: =+H115 -> ´1-03
B133: =+F1 -> P/depósito/transferencia en ICBC
B134: =+F2 -> Cta. Cte. $ N°538/02104658/84
B135: =+F3 -> CBU:0150538202000104658840
B136: =+F4 -> CUIT: 30-58026090-6 | E136: G A | F136: =+F118 -> 585388 | H136: =+D1 -> 46183
E137: G B | F137: =+F119 -> 135419.75
E138: D A | F138: =+F121 -> 0
E139: INT | F139: =+'RES CUENTA'!P15 -> 0
E140: s/Asamblea | F140: =+F120 -> 0
B141: =+$G$34 -> 46183 | C141: =+F123 -> 720807.75 | E141: TOT | F141: =+F123 -> 720807.75
E151: =+$B$1 -> 46143 | G151: =+$D$1 -> 46183
B154: =+B5 -> CANOPUS TRAVEL | E154: =+E1 -> URUGUAY 1025/27/29 CAP. FED. | H154: Unid. 4
H155: =+'RES CUENTA'!A16 -> ´2-04
B158: Expensas Gastos A | D158: =+'RES CUENTA'!H26 -> 6751880 | E158: =+'RES CUENTA'!G16 -> 8.67 | F158: =+D158*E158/100 -> 585388
B159: Expensas Gastos B | D159: =+'RES CUENTA'!J26 -> 1482120 | E159: =+'RES CUENTA'!I16 -> 9.1368954 | F159: =+D159*E159/100 -> 135419.75
B160: =+B120 -> s/Asamblea | D160: 0 | E160: 0 | F160: =+'RES CUENTA'!L15 -> 0
B161: Deuda Anterior | D161: =+'RES CUENTA'!O16 -> 0 | E161: 0 | F161: =+D161 -> 0
B162: Intereses | D162: =+'RES CUENTA'!P16 -> 0 | E162: 0 | F162: =+D162 -> 0
...

Sheet RET GCIA
D8: Enero | E8: Feb | F8: Marz | G8: Ab | H8: May | I8: TOTAL | J8: Gni | K8: Esposa | L8: Hijos | M8: Otras cargas | N8: Ded Esp
A9: García: Sueldo neto de 04/08 | D9: =+[8]Recibo!$I$51 -> 3168.4548 | E9: =+[8]Recibo!$I$51 -> 3168.4548 | F9: =+[9]Recibo!$I$51 -> 3400.759 | G9: =+[10]Recibo!$I$103 -> 3820.1955 | I9: =SUM(D9:H9) -> 13557.864
D10: =-[8]Recibo!$J$51 -> -675.25751 | E10: =-[11]Recibo!$J$199 -> -511.10798 | F10: =-[9]Recibo!$J$51 -> -723.30939 | G10: =-[10]Recibo!$J$103 -> -813.24106 | I10: =SUM(D10:H10) -> -2722.9159
D11: =SUM(D9:D10) -> 2493.1973 | E11: =SUM(E9:E10) -> 2657.3468 | F11: =SUM(F9:F10) -> 2677.4496 | G11: =SUM(G9:G10) -> 3006.9544 | I11: =SUM(D11:H11) -> 10834.948 | J11: -3125 | K11: -3335 | L11: =-1665*4 -> -6660 | N11: -3125

Sheet Hoja2
A1: Local
A2: enero | B2: 2002 | C2: 593 | D2: 2950
A3: feb | C3: 720 | D3: 3589
A4: abrul | B4: 2002 | C4: 622 | D4: 3100
A6: mayo | C6: 697 | D6: 3472
A7: julio | B7: 2002 | C7: 677 | D7: 3379
A8: agost | C8: 689 | D8: 3430
A9: set | C9: 687 | D9: 3427
A10: dic | B10: 2002 | C10: 667 | D10: 3327
A11: enero | B11: 2003 | C11: 646 | D11: 3219
A12: feb | C12: 881 | D12: 4391
A13: marz | C13: 689 | D13: 3436
A14: abruil | C14: 680
A15: mayo | C15: 780

Sheet Hoja1
A2: CONSORCIO SANTIAGO DEL ESTERO 338
A4: DETERMINACIÓN DE LAS COBRANZAS Y DE LOS SALDOS PENDIENTES DE COBRO AL 06/06/03
A7: Deuda anterior incluye intereses | E7: 60393.6
A8: Cobrado | E8: =-8052.31 -> -8052.31
A9: Deuda anterior (solamente capital) | E9: -50960.07
A10: Intereses pedientes de cobro correspondiente a deuda anterior | E10: =-'RES CUENTA'!#REF!+0.9 -> #REF!
A11: Importe incluido en Cobranzas y no en resumen de cuenta por no haber sido identificado | E11: 100
A12: Control | E12: =SUM(E7:E11) -> #REF!

Sheet Hoja3
C8: 44774 | D8: 560 | E8: 619
C9: 44805 | D9: 560 | E9: 637
C10: 44835 | D10: 680 | E10: 657
C11: 44866 | D11: 680 | E11: 706
C12: 44896 | D12: 925 | E12: 879
C13: 44927 | D13: 925 | E13: 940
C14: 44958 | D14: 925 | E14: 964
C15: TOTAL | D15: =SUM(D8:D14) -> 5255 | E15: =SUM(E8:E14) -> 5402
G16: 980
G17: 925
G18: =+G16-G17 -> 55
G19: =+G18/G17 -> 0.059459459
